[
{"current_level": 1, "leaf_id": "ce23633c-4cc5-11ec-955f-3af9d3e9a6f0", "parents": "root", "rule": "else: return 'True'", "feature_idx": -1, "feature_name": "", "instances": 51, "metric": 0, "return_statement": 0, "tree_id": 0}, 
{"current_level": 1, "leaf_id": "ce2a15d8-4cc5-11ec-955f-3af9d3e9a6f0", "parents": "root", "rule": "if obj[10]<=6:", "feature_idx": 10, "feature_name": "Income", "instances": 51, "metric": 0.9863676072907088, "return_statement": 0, "tree_id": 0}, 
{"current_level": 2, "leaf_id": "ce48e4c2-4cc5-11ec-955f-3af9d3e9a6f0", "parents": "ce2a15d8-4cc5-11ec-955f-3af9d3e9a6f0", "rule": "else: return 'True'", "feature_idx": -1, "feature_name": "", "instances": 46, "metric": 0, "return_statement": 0, "tree_id": 0}, 
{"current_level": 2, "leaf_id": "ce4ac99a-4cc5-11ec-955f-3af9d3e9a6f0", "parents": "ce2a15d8-4cc5-11ec-955f-3af9d3e9a6f0", "rule": "if obj[6]<=4:", "feature_idx": 6, "feature_name": "Age", "instances": 46, "metric": 0.9986359641585718, "return_statement": 0, "tree_id": 0}, 
{"current_level": 3, "leaf_id": "ce6686f8-4cc5-11ec-955f-3af9d3e9a6f0", "parents": "ce4ac99a-4cc5-11ec-955f-3af9d3e9a6f0", "rule": "else: return 'False'", "feature_idx": -1, "feature_name": "", "instances": 42, "metric": 0, "return_statement": 0, "tree_id": 0}, 
{"current_level": 3, "leaf_id": "ce683340-4cc5-11ec-955f-3af9d3e9a6f0", "parents": "ce4ac99a-4cc5-11ec-955f-3af9d3e9a6f0", "rule": "if obj[15]<=2:", "feature_idx": 15, "feature_name": "Distance", "instances": 42, "metric": 0.9983636725938131, "return_statement": 0, "tree_id": 0}, 
{"current_level": 4, "leaf_id": "ce844e72-4cc5-11ec-955f-3af9d3e9a6f0", "parents": "ce683340-4cc5-11ec-955f-3af9d3e9a6f0", "rule": "else: return 'False'", "feature_idx": -1, "feature_name": "", "instances": 38, "metric": 0, "return_statement": 0, "tree_id": 0}, 
{"current_level": 4, "leaf_id": "ce869cb8-4cc5-11ec-955f-3af9d3e9a6f0", "parents": "ce683340-4cc5-11ec-955f-3af9d3e9a6f0", "rule": "if obj[3]>1:", "feature_idx": 3, "feature_name": "Coupon", "instances": 38, "metric": 0.9980008838722996, "return_statement": 0, "tree_id": 0}, 
{"current_level": 5, "leaf_id": "cea253ea-4cc5-11ec-955f-3af9d3e9a6f0", "parents": "ce869cb8-4cc5-11ec-955f-3af9d3e9a6f0", "rule": "else: return 'True'", "feature_idx": -1, "feature_name": "", "instances": 27, "metric": 0, "return_statement": 0, "tree_id": 0}, 
{"current_level": 5, "leaf_id": "cea4d73c-4cc5-11ec-955f-3af9d3e9a6f0", "parents": "ce869cb8-4cc5-11ec-955f-3af9d3e9a6f0", "rule": "if obj[2]<=2:", "feature_idx": 2, "feature_name": "Time", "instances": 27, "metric": 0.9509560484549725, "return_statement": 0, "tree_id": 0}, 
{"current_level": 6, "leaf_id": "ceb9df92-4cc5-11ec-955f-3af9d3e9a6f0", "parents": "cea4d73c-4cc5-11ec-955f-3af9d3e9a6f0", "rule": "else: return 'True'", "feature_idx": -1, "feature_name": "", "instances": 19, "metric": 0, "return_statement": 0, "tree_id": 0}, 
{"current_level": 6, "leaf_id": "cebc3954-4cc5-11ec-955f-3af9d3e9a6f0", "parents": "cea4d73c-4cc5-11ec-955f-3af9d3e9a6f0", "rule": "if obj[9]<=12:", "feature_idx": 9, "feature_name": "Occupation", "instances": 19, "metric": 0.9980008838722996, "return_statement": 0, "tree_id": 0}, 
{"current_level": 7, "leaf_id": "ceccf78a-4cc5-11ec-955f-3af9d3e9a6f0", "parents": "cebc3954-4cc5-11ec-955f-3af9d3e9a6f0", "rule": "else: return 'False'", "feature_idx": -1, "feature_name": "", "instances": 17, "metric": 0, "return_statement": 0, "tree_id": 0}, 
{"current_level": 7, "leaf_id": "cecf1c18-4cc5-11ec-955f-3af9d3e9a6f0", "parents": "cebc3954-4cc5-11ec-955f-3af9d3e9a6f0", "rule": "if obj[11]<=2.0:", "feature_idx": 11, "feature_name": "Bar", "instances": 17, "metric": 0.9975025463691153, "return_statement": 0, "tree_id": 0}, 
{"current_level": 8, "leaf_id": "cedc6ecc-4cc5-11ec-955f-3af9d3e9a6f0", "parents": "cecf1c18-4cc5-11ec-955f-3af9d3e9a6f0", "rule": "else: return 'True'", "feature_idx": -1, "feature_name": "", "instances": 14, "metric": 0, "return_statement": 0, "tree_id": 0}, 
{"current_level": 8, "leaf_id": "cede4b66-4cc5-11ec-955f-3af9d3e9a6f0", "parents": "cecf1c18-4cc5-11ec-955f-3af9d3e9a6f0", "rule": "if obj[8]<=3:", "feature_idx": 8, "feature_name": "Education", "instances": 14, "metric": 0.9852281360342516, "return_statement": 0, "tree_id": 0}, 
{"current_level": 9, "leaf_id": "cee903ee-4cc5-11ec-955f-3af9d3e9a6f0", "parents": "cede4b66-4cc5-11ec-955f-3af9d3e9a6f0", "rule": "else: return 'True'", "feature_idx": -1, "feature_name": "", "instances": 11, "metric": 0, "return_statement": 0, "tree_id": 0}, 
{"current_level": 9, "leaf_id": "ceebe58c-4cc5-11ec-955f-3af9d3e9a6f0", "parents": "cede4b66-4cc5-11ec-955f-3af9d3e9a6f0", "rule": "if obj[4]>0:", "feature_idx": 4, "feature_name": "Coupon_validity", "instances": 11, "metric": 0.9940302114769565, "return_statement": 0, "tree_id": 0}, 
{"current_level": 10, "leaf_id": "cef48fe8-4cc5-11ec-955f-3af9d3e9a6f0", "parents": "ceebe58c-4cc5-11ec-955f-3af9d3e9a6f0", "rule": "else: return 'True'", "feature_idx": -1, "feature_name": "", "instances": 6, "metric": 0, "return_statement": 0, "tree_id": 0}, 
{"current_level": 10, "leaf_id": "cef72122-4cc5-11ec-955f-3af9d3e9a6f0", "parents": "ceebe58c-4cc5-11ec-955f-3af9d3e9a6f0", "rule": "if obj[0]>0:", "feature_idx": 0, "feature_name": "Passanger", "instances": 6, "metric": 0.6500224216483541, "return_statement": 0, "tree_id": 0}, 
{"current_level": 11, "leaf_id": "cef72398-4cc5-11ec-955f-3af9d3e9a6f0", "parents": "cef72122-4cc5-11ec-955f-3af9d3e9a6f0", "rule": "return 'False'", "feature_idx": 0, "feature_name": "Passanger", "instances": 6, "metric": 0, "return_statement": 1, "tree_id": 0}, 
{"current_level": 10, "leaf_id": "cef9ee16-4cc5-11ec-955f-3af9d3e9a6f0", "parents": "ceebe58c-4cc5-11ec-955f-3af9d3e9a6f0", "rule": "if obj[0]<=0:", "feature_idx": 0, "feature_name": "Passanger", "instances": 6, "metric": 0.6500224216483541, "return_statement": 0, "tree_id": 0}, 
{"current_level": 11, "leaf_id": "cefe5c12-4cc5-11ec-955f-3af9d3e9a6f0", "parents": "cef9ee16-4cc5-11ec-955f-3af9d3e9a6f0", "rule": "else: return 'False'", "feature_idx": -1, "feature_name": "", "instances": 2, "metric": 0, "return_statement": 0, "tree_id": 0}, 
{"current_level": 11, "leaf_id": "cf005f6c-4cc5-11ec-955f-3af9d3e9a6f0", "parents": "cef9ee16-4cc5-11ec-955f-3af9d3e9a6f0", "rule": "if obj[1]<=0:", "feature_idx": 1, "feature_name": "Weather", "instances": 2, "metric": 1.0, "return_statement": 0, "tree_id": 0}, 
{"current_level": 12, "leaf_id": "cf006188-4cc5-11ec-955f-3af9d3e9a6f0", "parents": "cf005f6c-4cc5-11ec-955f-3af9d3e9a6f0", "rule": "return 'True'", "feature_idx": 1, "feature_name": "Weather", "instances": 2, "metric": 0, "return_statement": 1, "tree_id": 0}, 
{"current_level": 11, "leaf_id": "cf034bf0-4cc5-11ec-955f-3af9d3e9a6f0", "parents": "cef9ee16-4cc5-11ec-955f-3af9d3e9a6f0", "rule": "if obj[1]>0:", "feature_idx": 1, "feature_name": "Weather", "instances": 2, "metric": 1.0, "return_statement": 0, "tree_id": 0}, 
{"current_level": 12, "leaf_id": "cf034dee-4cc5-11ec-955f-3af9d3e9a6f0", "parents": "cf034bf0-4cc5-11ec-955f-3af9d3e9a6f0", "rule": "return 'False'", "feature_idx": 1, "feature_name": "Weather", "instances": 2, "metric": 0, "return_statement": 1, "tree_id": 0}, 
{"current_level": 9, "leaf_id": "cf0add20-4cc5-11ec-955f-3af9d3e9a6f0", "parents": "cede4b66-4cc5-11ec-955f-3af9d3e9a6f0", "rule": "if obj[4]<=0:", "feature_idx": 4, "feature_name": "Coupon_validity", "instances": 11, "metric": 0.9940302114769565, "return_statement": 0, "tree_id": 0}, 
{"current_level": 10, "leaf_id": "cf125104-4cc5-11ec-955f-3af9d3e9a6f0", "parents": "cf0add20-4cc5-11ec-955f-3af9d3e9a6f0", "rule": "else: return 'True'", "feature_idx": -1, "feature_name": "", "instances": 5, "metric": 0, "return_statement": 0, "tree_id": 0}, 
{"current_level": 10, "leaf_id": "cf149b3a-4cc5-11ec-955f-3af9d3e9a6f0", "parents": "cf0add20-4cc5-11ec-955f-3af9d3e9a6f0", "rule": "if obj[0]>2:", "feature_idx": 0, "feature_name": "Passanger", "instances": 5, "metric": 0.7219280948873623, "return_statement": 0, "tree_id": 0}, 
{"current_level": 11, "leaf_id": "cf19f80a-4cc5-11ec-955f-3af9d3e9a6f0", "parents": "cf149b3a-4cc5-11ec-955f-3af9d3e9a6f0", "rule": "else: return 'False'", "feature_idx": -1, "feature_name": "", "instances": 3, "metric": 0, "return_statement": 0, "tree_id": 0}, 
{"current_level": 11, "leaf_id": "cf1c0d16-4cc5-11ec-955f-3af9d3e9a6f0", "parents": "cf149b3a-4cc5-11ec-955f-3af9d3e9a6f0", "rule": "if obj[12]>0.0:", "feature_idx": 12, "feature_name": "Coffeehouse", "instances": 3, "metric": 0.9182958340544896, "return_statement": 0, "tree_id": 0}, 
{"current_level": 12, "leaf_id": "cf1c0ece-4cc5-11ec-955f-3af9d3e9a6f0", "parents": "cf1c0d16-4cc5-11ec-955f-3af9d3e9a6f0", "rule": "return 'True'", "feature_idx": 12, "feature_name": "Coffeehouse", "instances": 3, "metric": 0, "return_statement": 1, "tree_id": 0}, 
{"current_level": 11, "leaf_id": "cf1e407c-4cc5-11ec-955f-3af9d3e9a6f0", "parents": "cf149b3a-4cc5-11ec-955f-3af9d3e9a6f0", "rule": "if obj[12]<=0.0:", "feature_idx": 12, "feature_name": "Coffeehouse", "instances": 3, "metric": 0.9182958340544896, "return_statement": 0, "tree_id": 0}, 
{"current_level": 12, "leaf_id": "cf1e4234-4cc5-11ec-955f-3af9d3e9a6f0", "parents": "cf1e407c-4cc5-11ec-955f-3af9d3e9a6f0", "rule": "return 'False'", "feature_idx": 12, "feature_name": "Coffeehouse", "instances": 3, "metric": 0, "return_statement": 1, "tree_id": 0}, 
{"current_level": 10, "leaf_id": "cf22714c-4cc5-11ec-955f-3af9d3e9a6f0", "parents": "cf0add20-4cc5-11ec-955f-3af9d3e9a6f0", "rule": "if obj[0]<=2:", "feature_idx": 0, "feature_name": "Passanger", "instances": 5, "metric": 0.7219280948873623, "return_statement": 0, "tree_id": 0}, 
{"current_level": 11, "leaf_id": "cf227322-4cc5-11ec-955f-3af9d3e9a6f0", "parents": "cf22714c-4cc5-11ec-955f-3af9d3e9a6f0", "rule": "return 'True'", "feature_idx": 0, "feature_name": "Passanger", "instances": 5, "metric": 0, "return_statement": 1, "tree_id": 0}, 
{"current_level": 8, "leaf_id": "cf2a4a16-4cc5-11ec-955f-3af9d3e9a6f0", "parents": "cecf1c18-4cc5-11ec-955f-3af9d3e9a6f0", "rule": "if obj[8]>3:", "feature_idx": 8, "feature_name": "Education", "instances": 14, "metric": 0.9852281360342516, "return_statement": 0, "tree_id": 0}, 
{"current_level": 9, "leaf_id": "cf2a4c14-4cc5-11ec-955f-3af9d3e9a6f0", "parents": "cf2a4a16-4cc5-11ec-955f-3af9d3e9a6f0", "rule": "return 'True'", "feature_idx": 8, "feature_name": "Education", "instances": 14, "metric": 0, "return_statement": 1, "tree_id": 0}, 
{"current_level": 7, "leaf_id": "cf2f4b88-4cc5-11ec-955f-3af9d3e9a6f0", "parents": "cebc3954-4cc5-11ec-955f-3af9d3e9a6f0", "rule": "if obj[11]>2.0:", "feature_idx": 11, "feature_name": "Bar", "instances": 17, "metric": 0.9975025463691153, "return_statement": 0, "tree_id": 0}, 
{"current_level": 8, "leaf_id": "cf2f4d86-4cc5-11ec-955f-3af9d3e9a6f0", "parents": "cf2f4b88-4cc5-11ec-955f-3af9d3e9a6f0", "rule": "return 'False'", "feature_idx": 11, "feature_name": "Bar", "instances": 17, "metric": 0, "return_statement": 1, "tree_id": 0}, 
{"current_level": 6, "leaf_id": "cf33575a-4cc5-11ec-955f-3af9d3e9a6f0", "parents": "cea4d73c-4cc5-11ec-955f-3af9d3e9a6f0", "rule": "if obj[9]>12:", "feature_idx": 9, "feature_name": "Occupation", "instances": 19, "metric": 0.9980008838722996, "return_statement": 0, "tree_id": 0}, 
{"current_level": 7, "leaf_id": "cf335926-4cc5-11ec-955f-3af9d3e9a6f0", "parents": "cf33575a-4cc5-11ec-955f-3af9d3e9a6f0", "rule": "return 'True'", "feature_idx": 9, "feature_name": "Occupation", "instances": 19, "metric": 0, "return_statement": 1, "tree_id": 0}, 
{"current_level": 5, "leaf_id": "cf374d42-4cc5-11ec-955f-3af9d3e9a6f0", "parents": "ce869cb8-4cc5-11ec-955f-3af9d3e9a6f0", "rule": "if obj[2]>2:", "feature_idx": 2, "feature_name": "Time", "instances": 27, "metric": 0.9509560484549725, "return_statement": 0, "tree_id": 0}, 
{"current_level": 6, "leaf_id": "cf4594f6-4cc5-11ec-955f-3af9d3e9a6f0", "parents": "cf374d42-4cc5-11ec-955f-3af9d3e9a6f0", "rule": "else: return 'False'", "feature_idx": -1, "feature_name": "", "instances": 8, "metric": 0, "return_statement": 0, "tree_id": 0}, 
{"current_level": 6, "leaf_id": "cf47956c-4cc5-11ec-955f-3af9d3e9a6f0", "parents": "cf374d42-4cc5-11ec-955f-3af9d3e9a6f0", "rule": "if obj[0]>0:", "feature_idx": 0, "feature_name": "Passanger", "instances": 8, "metric": 0.5435644431995964, "return_statement": 0, "tree_id": 0}, 
{"current_level": 7, "leaf_id": "cf479760-4cc5-11ec-955f-3af9d3e9a6f0", "parents": "cf47956c-4cc5-11ec-955f-3af9d3e9a6f0", "rule": "return 'True'", "feature_idx": 0, "feature_name": "Passanger", "instances": 8, "metric": 0, "return_statement": 1, "tree_id": 0}, 
{"current_level": 6, "leaf_id": "cf49d61a-4cc5-11ec-955f-3af9d3e9a6f0", "parents": "cf374d42-4cc5-11ec-955f-3af9d3e9a6f0", "rule": "if obj[0]<=0:", "feature_idx": 0, "feature_name": "Passanger", "instances": 8, "metric": 0.5435644431995964, "return_statement": 0, "tree_id": 0}, 
{"current_level": 7, "leaf_id": "cf51e3aa-4cc5-11ec-955f-3af9d3e9a6f0", "parents": "cf49d61a-4cc5-11ec-955f-3af9d3e9a6f0", "rule": "else: return 'True'", "feature_idx": -1, "feature_name": "", "instances": 2, "metric": 0, "return_statement": 0, "tree_id": 0}, 
{"current_level": 7, "leaf_id": "cf53b1e4-4cc5-11ec-955f-3af9d3e9a6f0", "parents": "cf49d61a-4cc5-11ec-955f-3af9d3e9a6f0", "rule": "if obj[1]>0:", "feature_idx": 1, "feature_name": "Weather", "instances": 2, "metric": 1.0, "return_statement": 0, "tree_id": 0}, 
{"current_level": 8, "leaf_id": "cf53b39c-4cc5-11ec-955f-3af9d3e9a6f0", "parents": "cf53b1e4-4cc5-11ec-955f-3af9d3e9a6f0", "rule": "return 'False'", "feature_idx": 1, "feature_name": "Weather", "instances": 2, "metric": 0, "return_statement": 1, "tree_id": 0}, 
{"current_level": 7, "leaf_id": "cf55ce52-4cc5-11ec-955f-3af9d3e9a6f0", "parents": "cf49d61a-4cc5-11ec-955f-3af9d3e9a6f0", "rule": "if obj[1]<=0:", "feature_idx": 1, "feature_name": "Weather", "instances": 2, "metric": 1.0, "return_statement": 0, "tree_id": 0}, 
{"current_level": 8, "leaf_id": "cf55d00a-4cc5-11ec-955f-3af9d3e9a6f0", "parents": "cf55ce52-4cc5-11ec-955f-3af9d3e9a6f0", "rule": "return 'True'", "feature_idx": 1, "feature_name": "Weather", "instances": 2, "metric": 0, "return_statement": 1, "tree_id": 0}, 
{"current_level": 4, "leaf_id": "cf5e6f6c-4cc5-11ec-955f-3af9d3e9a6f0", "parents": "ce683340-4cc5-11ec-955f-3af9d3e9a6f0", "rule": "if obj[3]<=1:", "feature_idx": 3, "feature_name": "Coupon", "instances": 38, "metric": 0.9980008838722996, "return_statement": 0, "tree_id": 0}, 
{"current_level": 5, "leaf_id": "cf70a9ac-4cc5-11ec-955f-3af9d3e9a6f0", "parents": "cf5e6f6c-4cc5-11ec-955f-3af9d3e9a6f0", "rule": "else: return 'True'", "feature_idx": -1, "feature_name": "", "instances": 11, "metric": 0, "return_statement": 0, "tree_id": 0}, 
{"current_level": 5, "leaf_id": "cf7298b6-4cc5-11ec-955f-3af9d3e9a6f0", "parents": "cf5e6f6c-4cc5-11ec-955f-3af9d3e9a6f0", "rule": "if obj[9]<=7:", "feature_idx": 9, "feature_name": "Occupation", "instances": 11, "metric": 0.8453509366224365, "return_statement": 0, "tree_id": 0}, 
{"current_level": 6, "leaf_id": "cf729aa0-4cc5-11ec-955f-3af9d3e9a6f0", "parents": "cf7298b6-4cc5-11ec-955f-3af9d3e9a6f0", "rule": "return 'False'", "feature_idx": 9, "feature_name": "Occupation", "instances": 11, "metric": 0, "return_statement": 1, "tree_id": 0}, 
{"current_level": 5, "leaf_id": "cf750b82-4cc5-11ec-955f-3af9d3e9a6f0", "parents": "cf5e6f6c-4cc5-11ec-955f-3af9d3e9a6f0", "rule": "if obj[9]>7:", "feature_idx": 9, "feature_name": "Occupation", "instances": 11, "metric": 0.8453509366224365, "return_statement": 0, "tree_id": 0}, 
{"current_level": 6, "leaf_id": "cf8100f4-4cc5-11ec-955f-3af9d3e9a6f0", "parents": "cf750b82-4cc5-11ec-955f-3af9d3e9a6f0", "rule": "else: return 'False'", "feature_idx": -1, "feature_name": "", "instances": 5, "metric": 0, "return_statement": 0, "tree_id": 0}, 
{"current_level": 6, "leaf_id": "cf82da0a-4cc5-11ec-955f-3af9d3e9a6f0", "parents": "cf750b82-4cc5-11ec-955f-3af9d3e9a6f0", "rule": "if obj[11]<=2.0:", "feature_idx": 11, "feature_name": "Bar", "instances": 5, "metric": 0.9709505944546686, "return_statement": 0, "tree_id": 0}, 
{"current_level": 7, "leaf_id": "cf82dbf4-4cc5-11ec-955f-3af9d3e9a6f0", "parents": "cf82da0a-4cc5-11ec-955f-3af9d3e9a6f0", "rule": "return 'True'", "feature_idx": 11, "feature_name": "Bar", "instances": 5, "metric": 0, "return_statement": 1, "tree_id": 0}, 
{"current_level": 6, "leaf_id": "cf8544ac-4cc5-11ec-955f-3af9d3e9a6f0", "parents": "cf750b82-4cc5-11ec-955f-3af9d3e9a6f0", "rule": "if obj[11]>2.0:", "feature_idx": 11, "feature_name": "Bar", "instances": 5, "metric": 0.9709505944546686, "return_statement": 0, "tree_id": 0}, 
{"current_level": 7, "leaf_id": "cf85468c-4cc5-11ec-955f-3af9d3e9a6f0", "parents": "cf8544ac-4cc5-11ec-955f-3af9d3e9a6f0", "rule": "return 'False'", "feature_idx": 11, "feature_name": "Bar", "instances": 5, "metric": 0, "return_statement": 1, "tree_id": 0}, 
{"current_level": 3, "leaf_id": "cf8dba56-4cc5-11ec-955f-3af9d3e9a6f0", "parents": "ce4ac99a-4cc5-11ec-955f-3af9d3e9a6f0", "rule": "if obj[15]>2:", "feature_idx": 15, "feature_name": "Distance", "instances": 42, "metric": 0.9983636725938131, "return_statement": 0, "tree_id": 0}, 
{"current_level": 4, "leaf_id": "cf8dbc2c-4cc5-11ec-955f-3af9d3e9a6f0", "parents": "cf8dba56-4cc5-11ec-955f-3af9d3e9a6f0", "rule": "return 'False'", "feature_idx": 15, "feature_name": "Distance", "instances": 42, "metric": 0, "return_statement": 1, "tree_id": 0}, 
{"current_level": 2, "leaf_id": "cf921c86-4cc5-11ec-955f-3af9d3e9a6f0", "parents": "ce2a15d8-4cc5-11ec-955f-3af9d3e9a6f0", "rule": "if obj[6]>4:", "feature_idx": 6, "feature_name": "Age", "instances": 46, "metric": 0.9986359641585718, "return_statement": 0, "tree_id": 0}, 
{"current_level": 3, "leaf_id": "cf921e5c-4cc5-11ec-955f-3af9d3e9a6f0", "parents": "cf921c86-4cc5-11ec-955f-3af9d3e9a6f0", "rule": "return 'True'", "feature_idx": 6, "feature_name": "Age", "instances": 46, "metric": 0, "return_statement": 1, "tree_id": 0}, 
{"current_level": 1, "leaf_id": "cf96b8a4-4cc5-11ec-955f-3af9d3e9a6f0", "parents": "root", "rule": "if obj[10]>6:", "feature_idx": 10, "feature_name": "Income", "instances": 51, "metric": 0.9863676072907088, "return_statement": 0, "tree_id": 0}, 
{"current_level": 2, "leaf_id": "cf96ba52-4cc5-11ec-955f-3af9d3e9a6f0", "parents": "cf96b8a4-4cc5-11ec-955f-3af9d3e9a6f0", "rule": "return 'True'", "feature_idx": 10, "feature_name": "Income", "instances": 51, "metric": 0, "return_statement": 1, "tree_id": 0}
]