[
{"current_level": 1, "leaf_id": "85797838-4cc5-11ec-a9c9-3af9d3e9a6f0", "parents": "root", "rule": "else: return 'False'", "feature_idx": -1, "feature_name": "", "instances": 127, "metric": 0, "return_statement": 0, "tree_id": 1}, 
{"current_level": 1, "leaf_id": "857f3002-4cc5-11ec-a9c9-3af9d3e9a6f0", "parents": "root", "rule": "if obj[2]>1:", "feature_idx": 2, "feature_name": "Coupon", "instances": 127, "metric": 0.9801860005643561, "return_statement": 0, "tree_id": 1}, 
{"current_level": 2, "leaf_id": "85a267c0-4cc5-11ec-a9c9-3af9d3e9a6f0", "parents": "857f3002-4cc5-11ec-a9c9-3af9d3e9a6f0", "rule": "else: return 'False'", "feature_idx": -1, "feature_name": "", "instances": 91, "metric": 0, "return_statement": 0, "tree_id": 1}, 
{"current_level": 2, "leaf_id": "85a453aa-4cc5-11ec-a9c9-3af9d3e9a6f0", "parents": "857f3002-4cc5-11ec-a9c9-3af9d3e9a6f0", "rule": "if obj[9]>-1.0:", "feature_idx": 9, "feature_name": "Bar", "instances": 91, "metric": 0.9254482516437046, "return_statement": 0, "tree_id": 1}, 
{"current_level": 3, "leaf_id": "85c3aaac-4cc5-11ec-a9c9-3af9d3e9a6f0", "parents": "85a453aa-4cc5-11ec-a9c9-3af9d3e9a6f0", "rule": "else: return 'False'", "feature_idx": -1, "feature_name": "", "instances": 89, "metric": 0, "return_statement": 0, "tree_id": 1}, 
{"current_level": 3, "leaf_id": "85c59128-4cc5-11ec-a9c9-3af9d3e9a6f0", "parents": "85a453aa-4cc5-11ec-a9c9-3af9d3e9a6f0", "rule": "if obj[6]<=2:", "feature_idx": 6, "feature_name": "Education", "instances": 89, "metric": 0.9106223680988619, "return_statement": 0, "tree_id": 1}, 
{"current_level": 4, "leaf_id": "85e124f6-4cc5-11ec-a9c9-3af9d3e9a6f0", "parents": "85c59128-4cc5-11ec-a9c9-3af9d3e9a6f0", "rule": "else: return 'False'", "feature_idx": -1, "feature_name": "", "instances": 75, "metric": 0, "return_statement": 0, "tree_id": 1}, 
{"current_level": 4, "leaf_id": "85e498ac-4cc5-11ec-a9c9-3af9d3e9a6f0", "parents": "85c59128-4cc5-11ec-a9c9-3af9d3e9a6f0", "rule": "if obj[4]>0:", "feature_idx": 4, "feature_name": "Age", "instances": 75, "metric": 0.8554508105601307, "return_statement": 0, "tree_id": 1}, 
{"current_level": 5, "leaf_id": "85fc0cb2-4cc5-11ec-a9c9-3af9d3e9a6f0", "parents": "85e498ac-4cc5-11ec-a9c9-3af9d3e9a6f0", "rule": "else: return 'True'", "feature_idx": -1, "feature_name": "", "instances": 64, "metric": 0, "return_statement": 0, "tree_id": 1}, 
{"current_level": 5, "leaf_id": "85fdb2ce-4cc5-11ec-a9c9-3af9d3e9a6f0", "parents": "85e498ac-4cc5-11ec-a9c9-3af9d3e9a6f0", "rule": "if obj[7]>2:", "feature_idx": 7, "feature_name": "Occupation", "instances": 64, "metric": 0.7578784625383955, "return_statement": 0, "tree_id": 1}, 
{"current_level": 6, "leaf_id": "860d4220-4cc5-11ec-a9c9-3af9d3e9a6f0", "parents": "85fdb2ce-4cc5-11ec-a9c9-3af9d3e9a6f0", "rule": "else: return 'True'", "feature_idx": -1, "feature_name": "", "instances": 53, "metric": 0, "return_statement": 0, "tree_id": 1}, 
{"current_level": 6, "leaf_id": "860eeeea-4cc5-11ec-a9c9-3af9d3e9a6f0", "parents": "85fdb2ce-4cc5-11ec-a9c9-3af9d3e9a6f0", "rule": "if obj[10]>0.0:", "feature_idx": 10, "feature_name": "Coffeehouse", "instances": 53, "metric": 0.83294582353614, "return_statement": 0, "tree_id": 1}, 
{"current_level": 7, "leaf_id": "861c8910-4cc5-11ec-a9c9-3af9d3e9a6f0", "parents": "860eeeea-4cc5-11ec-a9c9-3af9d3e9a6f0", "rule": "else: return 'True'", "feature_idx": -1, "feature_name": "", "instances": 37, "metric": 0, "return_statement": 0, "tree_id": 1}, 
{"current_level": 7, "leaf_id": "861f49c0-4cc5-11ec-a9c9-3af9d3e9a6f0", "parents": "860eeeea-4cc5-11ec-a9c9-3af9d3e9a6f0", "rule": "if obj[0]<=1:", "feature_idx": 0, "feature_name": "Passanger", "instances": 37, "metric": 0.699772221773307, "return_statement": 0, "tree_id": 1}, 
{"current_level": 8, "leaf_id": "862ab328-4cc5-11ec-a9c9-3af9d3e9a6f0", "parents": "861f49c0-4cc5-11ec-a9c9-3af9d3e9a6f0", "rule": "else: return 'False'", "feature_idx": -1, "feature_name": "", "instances": 22, "metric": 0, "return_statement": 0, "tree_id": 1}, 
{"current_level": 8, "leaf_id": "862fca70-4cc5-11ec-a9c9-3af9d3e9a6f0", "parents": "861f49c0-4cc5-11ec-a9c9-3af9d3e9a6f0", "rule": "if obj[3]<=0:", "feature_idx": 3, "feature_name": "Gender", "instances": 22, "metric": 0.9023932827949789, "return_statement": 0, "tree_id": 1}, 
{"current_level": 9, "leaf_id": "863904be-4cc5-11ec-a9c9-3af9d3e9a6f0", "parents": "862fca70-4cc5-11ec-a9c9-3af9d3e9a6f0", "rule": "else: return 'False'", "feature_idx": -1, "feature_name": "", "instances": 14, "metric": 0, "return_statement": 0, "tree_id": 1}, 
{"current_level": 9, "leaf_id": "863ae572-4cc5-11ec-a9c9-3af9d3e9a6f0", "parents": "862fca70-4cc5-11ec-a9c9-3af9d3e9a6f0", "rule": "if obj[13]<=2:", "feature_idx": 13, "feature_name": "Distance", "instances": 14, "metric": 0.5916727785823275, "return_statement": 0, "tree_id": 1}, 
{"current_level": 10, "leaf_id": "863ae734-4cc5-11ec-a9c9-3af9d3e9a6f0", "parents": "863ae572-4cc5-11ec-a9c9-3af9d3e9a6f0", "rule": "return 'True'", "feature_idx": 13, "feature_name": "Distance", "instances": 14, "metric": 0, "return_statement": 1, "tree_id": 1}, 
{"current_level": 9, "leaf_id": "863ccc3e-4cc5-11ec-a9c9-3af9d3e9a6f0", "parents": "862fca70-4cc5-11ec-a9c9-3af9d3e9a6f0", "rule": "if obj[13]>2:", "feature_idx": 13, "feature_name": "Distance", "instances": 14, "metric": 0.5916727785823275, "return_statement": 0, "tree_id": 1}, 
{"current_level": 10, "leaf_id": "864208d4-4cc5-11ec-a9c9-3af9d3e9a6f0", "parents": "863ccc3e-4cc5-11ec-a9c9-3af9d3e9a6f0", "rule": "else: return 'True'", "feature_idx": -1, "feature_name": "", "instances": 4, "metric": 0, "return_statement": 0, "tree_id": 1}, 
{"current_level": 10, "leaf_id": "8644db22-4cc5-11ec-a9c9-3af9d3e9a6f0", "parents": "863ccc3e-4cc5-11ec-a9c9-3af9d3e9a6f0", "rule": "if obj[8]>0:", "feature_idx": 8, "feature_name": "Income", "instances": 4, "metric": 1.0, "return_statement": 0, "tree_id": 1}, 
{"current_level": 11, "leaf_id": "8648ea14-4cc5-11ec-a9c9-3af9d3e9a6f0", "parents": "8644db22-4cc5-11ec-a9c9-3af9d3e9a6f0", "rule": "else: return 'True'", "feature_idx": -1, "feature_name": "", "instances": 3, "metric": 0, "return_statement": 0, "tree_id": 1}, 
{"current_level": 11, "leaf_id": "864befc0-4cc5-11ec-a9c9-3af9d3e9a6f0", "parents": "8644db22-4cc5-11ec-a9c9-3af9d3e9a6f0", "rule": "if obj[11]>0.0:", "feature_idx": 11, "feature_name": "Restaurant20to50", "instances": 3, "metric": 0.9182958340544896, "return_statement": 0, "tree_id": 1}, 
{"current_level": 12, "leaf_id": "864bf18c-4cc5-11ec-a9c9-3af9d3e9a6f0", "parents": "864befc0-4cc5-11ec-a9c9-3af9d3e9a6f0", "rule": "return 'False'", "feature_idx": 11, "feature_name": "Restaurant20to50", "instances": 3, "metric": 0, "return_statement": 1, "tree_id": 1}, 
{"current_level": 11, "leaf_id": "864e2f42-4cc5-11ec-a9c9-3af9d3e9a6f0", "parents": "8644db22-4cc5-11ec-a9c9-3af9d3e9a6f0", "rule": "if obj[11]<=0.0:", "feature_idx": 11, "feature_name": "Restaurant20to50", "instances": 3, "metric": 0.9182958340544896, "return_statement": 0, "tree_id": 1}, 
{"current_level": 12, "leaf_id": "864e30fa-4cc5-11ec-a9c9-3af9d3e9a6f0", "parents": "864e2f42-4cc5-11ec-a9c9-3af9d3e9a6f0", "rule": "return 'True'", "feature_idx": 11, "feature_name": "Restaurant20to50", "instances": 3, "metric": 0, "return_statement": 1, "tree_id": 1}, 
{"current_level": 10, "leaf_id": "865301ca-4cc5-11ec-a9c9-3af9d3e9a6f0", "parents": "863ccc3e-4cc5-11ec-a9c9-3af9d3e9a6f0", "rule": "if obj[8]<=0:", "feature_idx": 8, "feature_name": "Income", "instances": 4, "metric": 1.0, "return_statement": 0, "tree_id": 1}, 
{"current_level": 11, "leaf_id": "865303a0-4cc5-11ec-a9c9-3af9d3e9a6f0", "parents": "865301ca-4cc5-11ec-a9c9-3af9d3e9a6f0", "rule": "return 'True'", "feature_idx": 8, "feature_name": "Income", "instances": 4, "metric": 0, "return_statement": 1, "tree_id": 1}, 
{"current_level": 8, "leaf_id": "8659cf28-4cc5-11ec-a9c9-3af9d3e9a6f0", "parents": "861f49c0-4cc5-11ec-a9c9-3af9d3e9a6f0", "rule": "if obj[3]>0:", "feature_idx": 3, "feature_name": "Gender", "instances": 22, "metric": 0.9023932827949789, "return_statement": 0, "tree_id": 1}, 
{"current_level": 9, "leaf_id": "866220b0-4cc5-11ec-a9c9-3af9d3e9a6f0", "parents": "8659cf28-4cc5-11ec-a9c9-3af9d3e9a6f0", "rule": "else: return 'True'", "feature_idx": -1, "feature_name": "", "instances": 8, "metric": 0, "return_statement": 0, "tree_id": 1}, 
{"current_level": 9, "leaf_id": "8665b9d2-4cc5-11ec-a9c9-3af9d3e9a6f0", "parents": "8659cf28-4cc5-11ec-a9c9-3af9d3e9a6f0", "rule": "if obj[8]>0:", "feature_idx": 8, "feature_name": "Income", "instances": 8, "metric": 0.9544340029249649, "return_statement": 0, "tree_id": 1}, 
{"current_level": 10, "leaf_id": "866b7db8-4cc5-11ec-a9c9-3af9d3e9a6f0", "parents": "8665b9d2-4cc5-11ec-a9c9-3af9d3e9a6f0", "rule": "else: return 'False'", "feature_idx": -1, "feature_name": "", "instances": 7, "metric": 0, "return_statement": 0, "tree_id": 1}, 
{"current_level": 10, "leaf_id": "866d4fda-4cc5-11ec-a9c9-3af9d3e9a6f0", "parents": "8665b9d2-4cc5-11ec-a9c9-3af9d3e9a6f0", "rule": "if obj[5]>0:", "feature_idx": 5, "feature_name": "Children", "instances": 7, "metric": 0.863120568566631, "return_statement": 0, "tree_id": 1}, 
{"current_level": 11, "leaf_id": "8671e69e-4cc5-11ec-a9c9-3af9d3e9a6f0", "parents": "866d4fda-4cc5-11ec-a9c9-3af9d3e9a6f0", "rule": "else: return 'False'", "feature_idx": -1, "feature_name": "", "instances": 4, "metric": 0, "return_statement": 0, "tree_id": 1}, 
{"current_level": 11, "leaf_id": "8678c2b6-4cc5-11ec-a9c9-3af9d3e9a6f0", "parents": "866d4fda-4cc5-11ec-a9c9-3af9d3e9a6f0", "rule": "if obj[1]<=1:", "feature_idx": 1, "feature_name": "Time", "instances": 4, "metric": 1.0, "return_statement": 0, "tree_id": 1}, 
{"current_level": 12, "leaf_id": "867c300e-4cc5-11ec-a9c9-3af9d3e9a6f0", "parents": "8678c2b6-4cc5-11ec-a9c9-3af9d3e9a6f0", "rule": "else: return 'False'", "feature_idx": -1, "feature_name": "", "instances": 3, "metric": 0, "return_statement": 0, "tree_id": 1}, 
{"current_level": 12, "leaf_id": "867e5f3c-4cc5-11ec-a9c9-3af9d3e9a6f0", "parents": "8678c2b6-4cc5-11ec-a9c9-3af9d3e9a6f0", "rule": "if obj[13]<=1:", "feature_idx": 13, "feature_name": "Distance", "instances": 3, "metric": 0.9182958340544896, "return_statement": 0, "tree_id": 1}, 
{"current_level": 13, "leaf_id": "867e6130-4cc5-11ec-a9c9-3af9d3e9a6f0", "parents": "867e5f3c-4cc5-11ec-a9c9-3af9d3e9a6f0", "rule": "return 'True'", "feature_idx": 13, "feature_name": "Distance", "instances": 3, "metric": 0, "return_statement": 1, "tree_id": 1}, 
{"current_level": 12, "leaf_id": "86811d6c-4cc5-11ec-a9c9-3af9d3e9a6f0", "parents": "8678c2b6-4cc5-11ec-a9c9-3af9d3e9a6f0", "rule": "if obj[13]>1:", "feature_idx": 13, "feature_name": "Distance", "instances": 3, "metric": 0.9182958340544896, "return_statement": 0, "tree_id": 1}, 
{"current_level": 13, "leaf_id": "86811f7e-4cc5-11ec-a9c9-3af9d3e9a6f0", "parents": "86811d6c-4cc5-11ec-a9c9-3af9d3e9a6f0", "rule": "return 'False'", "feature_idx": 13, "feature_name": "Distance", "instances": 3, "metric": 0, "return_statement": 1, "tree_id": 1}, 
{"current_level": 11, "leaf_id": "868691fc-4cc5-11ec-a9c9-3af9d3e9a6f0", "parents": "866d4fda-4cc5-11ec-a9c9-3af9d3e9a6f0", "rule": "if obj[1]>1:", "feature_idx": 1, "feature_name": "Time", "instances": 4, "metric": 1.0, "return_statement": 0, "tree_id": 1}, 
{"current_level": 12, "leaf_id": "86869404-4cc5-11ec-a9c9-3af9d3e9a6f0", "parents": "868691fc-4cc5-11ec-a9c9-3af9d3e9a6f0", "rule": "return 'False'", "feature_idx": 1, "feature_name": "Time", "instances": 4, "metric": 0, "return_statement": 1, "tree_id": 1}, 
{"current_level": 10, "leaf_id": "868c5dd0-4cc5-11ec-a9c9-3af9d3e9a6f0", "parents": "8665b9d2-4cc5-11ec-a9c9-3af9d3e9a6f0", "rule": "if obj[5]<=0:", "feature_idx": 5, "feature_name": "Children", "instances": 7, "metric": 0.863120568566631, "return_statement": 0, "tree_id": 1}, 
{"current_level": 11, "leaf_id": "868c6096-4cc5-11ec-a9c9-3af9d3e9a6f0", "parents": "868c5dd0-4cc5-11ec-a9c9-3af9d3e9a6f0", "rule": "return 'False'", "feature_idx": 5, "feature_name": "Children", "instances": 7, "metric": 0, "return_statement": 1, "tree_id": 1}, 
{"current_level": 9, "leaf_id": "86910182-4cc5-11ec-a9c9-3af9d3e9a6f0", "parents": "8659cf28-4cc5-11ec-a9c9-3af9d3e9a6f0", "rule": "if obj[8]<=0:", "feature_idx": 8, "feature_name": "Income", "instances": 8, "metric": 0.9544340029249649, "return_statement": 0, "tree_id": 1}, 
{"current_level": 10, "leaf_id": "86910376-4cc5-11ec-a9c9-3af9d3e9a6f0", "parents": "86910182-4cc5-11ec-a9c9-3af9d3e9a6f0", "rule": "return 'True'", "feature_idx": 8, "feature_name": "Income", "instances": 8, "metric": 0, "return_statement": 1, "tree_id": 1}, 
{"current_level": 7, "leaf_id": "86993f50-4cc5-11ec-a9c9-3af9d3e9a6f0", "parents": "860eeeea-4cc5-11ec-a9c9-3af9d3e9a6f0", "rule": "if obj[0]>1:", "feature_idx": 0, "feature_name": "Passanger", "instances": 37, "metric": 0.699772221773307, "return_statement": 0, "tree_id": 1}, 
{"current_level": 8, "leaf_id": "8699416c-4cc5-11ec-a9c9-3af9d3e9a6f0", "parents": "86993f50-4cc5-11ec-a9c9-3af9d3e9a6f0", "rule": "return 'True'", "feature_idx": 0, "feature_name": "Passanger", "instances": 37, "metric": 0, "return_statement": 1, "tree_id": 1}, 
{"current_level": 6, "leaf_id": "869e98a6-4cc5-11ec-a9c9-3af9d3e9a6f0", "parents": "85fdb2ce-4cc5-11ec-a9c9-3af9d3e9a6f0", "rule": "if obj[10]<=0.0:", "feature_idx": 10, "feature_name": "Coffeehouse", "instances": 53, "metric": 0.83294582353614, "return_statement": 0, "tree_id": 1}, 
{"current_level": 7, "leaf_id": "86abb374-4cc5-11ec-a9c9-3af9d3e9a6f0", "parents": "869e98a6-4cc5-11ec-a9c9-3af9d3e9a6f0", "rule": "else: return 'False'", "feature_idx": -1, "feature_name": "", "instances": 16, "metric": 0, "return_statement": 0, "tree_id": 1}, 
{"current_level": 7, "leaf_id": "86ae4e36-4cc5-11ec-a9c9-3af9d3e9a6f0", "parents": "869e98a6-4cc5-11ec-a9c9-3af9d3e9a6f0", "rule": "if obj[1]<=2:", "feature_idx": 1, "feature_name": "Time", "instances": 16, "metric": 0.9886994082884974, "return_statement": 0, "tree_id": 1}, 
{"current_level": 8, "leaf_id": "86b86862-4cc5-11ec-a9c9-3af9d3e9a6f0", "parents": "86ae4e36-4cc5-11ec-a9c9-3af9d3e9a6f0", "rule": "else: return 'False'", "feature_idx": -1, "feature_name": "", "instances": 12, "metric": 0, "return_statement": 0, "tree_id": 1}, 
{"current_level": 8, "leaf_id": "86ba7d78-4cc5-11ec-a9c9-3af9d3e9a6f0", "parents": "86ae4e36-4cc5-11ec-a9c9-3af9d3e9a6f0", "rule": "if obj[0]>0:", "feature_idx": 0, "feature_name": "Passanger", "instances": 12, "metric": 0.9182958340544896, "return_statement": 0, "tree_id": 1}, 
{"current_level": 9, "leaf_id": "86c2d3ba-4cc5-11ec-a9c9-3af9d3e9a6f0", "parents": "86ba7d78-4cc5-11ec-a9c9-3af9d3e9a6f0", "rule": "else: return 'True'", "feature_idx": -1, "feature_name": "", "instances": 11, "metric": 0, "return_statement": 0, "tree_id": 1}, 
{"current_level": 9, "leaf_id": "86c76010-4cc5-11ec-a9c9-3af9d3e9a6f0", "parents": "86ba7d78-4cc5-11ec-a9c9-3af9d3e9a6f0", "rule": "if obj[8]<=5:", "feature_idx": 8, "feature_name": "Income", "instances": 11, "metric": 0.8453509366224365, "return_statement": 0, "tree_id": 1}, 
{"current_level": 10, "leaf_id": "86cd6668-4cc5-11ec-a9c9-3af9d3e9a6f0", "parents": "86c76010-4cc5-11ec-a9c9-3af9d3e9a6f0", "rule": "else: return 'True'", "feature_idx": -1, "feature_name": "", "instances": 7, "metric": 0, "return_statement": 0, "tree_id": 1}, 
{"current_level": 10, "leaf_id": "86d13a04-4cc5-11ec-a9c9-3af9d3e9a6f0", "parents": "86c76010-4cc5-11ec-a9c9-3af9d3e9a6f0", "rule": "if obj[5]<=0:", "feature_idx": 5, "feature_name": "Children", "instances": 7, "metric": 0.5916727785823275, "return_statement": 0, "tree_id": 1}, 
{"current_level": 11, "leaf_id": "86d13bd0-4cc5-11ec-a9c9-3af9d3e9a6f0", "parents": "86d13a04-4cc5-11ec-a9c9-3af9d3e9a6f0", "rule": "return 'True'", "feature_idx": 5, "feature_name": "Children", "instances": 7, "metric": 0, "return_statement": 1, "tree_id": 1}, 
{"current_level": 10, "leaf_id": "86d3bcd4-4cc5-11ec-a9c9-3af9d3e9a6f0", "parents": "86c76010-4cc5-11ec-a9c9-3af9d3e9a6f0", "rule": "if obj[5]>0:", "feature_idx": 5, "feature_name": "Children", "instances": 7, "metric": 0.5916727785823275, "return_statement": 0, "tree_id": 1}, 
{"current_level": 11, "leaf_id": "86d7e1d8-4cc5-11ec-a9c9-3af9d3e9a6f0", "parents": "86d3bcd4-4cc5-11ec-a9c9-3af9d3e9a6f0", "rule": "else: return 'False'", "feature_idx": -1, "feature_name": "", "instances": 3, "metric": 0, "return_statement": 0, "tree_id": 1}, 
{"current_level": 11, "leaf_id": "86da0170-4cc5-11ec-a9c9-3af9d3e9a6f0", "parents": "86d3bcd4-4cc5-11ec-a9c9-3af9d3e9a6f0", "rule": "if obj[3]>0:", "feature_idx": 3, "feature_name": "Gender", "instances": 3, "metric": 0.9182958340544896, "return_statement": 0, "tree_id": 1}, 
{"current_level": 12, "leaf_id": "86da0364-4cc5-11ec-a9c9-3af9d3e9a6f0", "parents": "86da0170-4cc5-11ec-a9c9-3af9d3e9a6f0", "rule": "return 'True'", "feature_idx": 3, "feature_name": "Gender", "instances": 3, "metric": 0, "return_statement": 1, "tree_id": 1}, 
{"current_level": 11, "leaf_id": "86dcbb18-4cc5-11ec-a9c9-3af9d3e9a6f0", "parents": "86d3bcd4-4cc5-11ec-a9c9-3af9d3e9a6f0", "rule": "if obj[3]<=0:", "feature_idx": 3, "feature_name": "Gender", "instances": 3, "metric": 0.9182958340544896, "return_statement": 0, "tree_id": 1}, 
{"current_level": 12, "leaf_id": "86dcbd0c-4cc5-11ec-a9c9-3af9d3e9a6f0", "parents": "86dcbb18-4cc5-11ec-a9c9-3af9d3e9a6f0", "rule": "return 'False'", "feature_idx": 3, "feature_name": "Gender", "instances": 3, "metric": 0, "return_statement": 1, "tree_id": 1}, 
{"current_level": 9, "leaf_id": "86e44428-4cc5-11ec-a9c9-3af9d3e9a6f0", "parents": "86ba7d78-4cc5-11ec-a9c9-3af9d3e9a6f0", "rule": "if obj[8]>5:", "feature_idx": 8, "feature_name": "Income", "instances": 11, "metric": 0.8453509366224365, "return_statement": 0, "tree_id": 1}, 
{"current_level": 10, "leaf_id": "86e89fc8-4cc5-11ec-a9c9-3af9d3e9a6f0", "parents": "86e44428-4cc5-11ec-a9c9-3af9d3e9a6f0", "rule": "else: return 'False'", "feature_idx": -1, "feature_name": "", "instances": 4, "metric": 0, "return_statement": 0, "tree_id": 1}, 
{"current_level": 10, "leaf_id": "86ed4c44-4cc5-11ec-a9c9-3af9d3e9a6f0", "parents": "86e44428-4cc5-11ec-a9c9-3af9d3e9a6f0", "rule": "if obj[12]<=0:", "feature_idx": 12, "feature_name": "Direction_same", "instances": 4, "metric": 1.0, "return_statement": 0, "tree_id": 1}, 
{"current_level": 11, "leaf_id": "86f0bc3a-4cc5-11ec-a9c9-3af9d3e9a6f0", "parents": "86ed4c44-4cc5-11ec-a9c9-3af9d3e9a6f0", "rule": "else: return 'False'", "feature_idx": -1, "feature_name": "", "instances": 3, "metric": 0, "return_statement": 0, "tree_id": 1}, 
{"current_level": 11, "leaf_id": "86f3439c-4cc5-11ec-a9c9-3af9d3e9a6f0", "parents": "86ed4c44-4cc5-11ec-a9c9-3af9d3e9a6f0", "rule": "if obj[13]<=2:", "feature_idx": 13, "feature_name": "Distance", "instances": 3, "metric": 0.9182958340544896, "return_statement": 0, "tree_id": 1}, 
{"current_level": 12, "leaf_id": "86f3457c-4cc5-11ec-a9c9-3af9d3e9a6f0", "parents": "86f3439c-4cc5-11ec-a9c9-3af9d3e9a6f0", "rule": "return 'True'", "feature_idx": 13, "feature_name": "Distance", "instances": 3, "metric": 0, "return_statement": 1, "tree_id": 1}, 
{"current_level": 11, "leaf_id": "86f5c6d0-4cc5-11ec-a9c9-3af9d3e9a6f0", "parents": "86ed4c44-4cc5-11ec-a9c9-3af9d3e9a6f0", "rule": "if obj[13]>2:", "feature_idx": 13, "feature_name": "Distance", "instances": 3, "metric": 0.9182958340544896, "return_statement": 0, "tree_id": 1}, 
{"current_level": 12, "leaf_id": "86f5c8ce-4cc5-11ec-a9c9-3af9d3e9a6f0", "parents": "86f5c6d0-4cc5-11ec-a9c9-3af9d3e9a6f0", "rule": "return 'False'", "feature_idx": 13, "feature_name": "Distance", "instances": 3, "metric": 0, "return_statement": 1, "tree_id": 1}, 
{"current_level": 10, "leaf_id": "8703359a-4cc5-11ec-a9c9-3af9d3e9a6f0", "parents": "86e44428-4cc5-11ec-a9c9-3af9d3e9a6f0", "rule": "if obj[12]>0:", "feature_idx": 12, "feature_name": "Direction_same", "instances": 4, "metric": 1.0, "return_statement": 0, "tree_id": 1}, 
{"current_level": 11, "leaf_id": "8703393c-4cc5-11ec-a9c9-3af9d3e9a6f0", "parents": "8703359a-4cc5-11ec-a9c9-3af9d3e9a6f0", "rule": "return 'False'", "feature_idx": 12, "feature_name": "Direction_same", "instances": 4, "metric": 0, "return_statement": 1, "tree_id": 1}, 
{"current_level": 8, "leaf_id": "87108f10-4cc5-11ec-a9c9-3af9d3e9a6f0", "parents": "86ae4e36-4cc5-11ec-a9c9-3af9d3e9a6f0", "rule": "if obj[0]<=0:", "feature_idx": 0, "feature_name": "Passanger", "instances": 12, "metric": 0.9182958340544896, "return_statement": 0, "tree_id": 1}, 
{"current_level": 9, "leaf_id": "871091ae-4cc5-11ec-a9c9-3af9d3e9a6f0", "parents": "87108f10-4cc5-11ec-a9c9-3af9d3e9a6f0", "rule": "return 'False'", "feature_idx": 0, "feature_name": "Passanger", "instances": 12, "metric": 0, "return_statement": 1, "tree_id": 1}, 
{"current_level": 7, "leaf_id": "8717fa84-4cc5-11ec-a9c9-3af9d3e9a6f0", "parents": "869e98a6-4cc5-11ec-a9c9-3af9d3e9a6f0", "rule": "if obj[1]>2:", "feature_idx": 1, "feature_name": "Time", "instances": 16, "metric": 0.9886994082884974, "return_statement": 0, "tree_id": 1}, 
{"current_level": 8, "leaf_id": "872493ca-4cc5-11ec-a9c9-3af9d3e9a6f0", "parents": "8717fa84-4cc5-11ec-a9c9-3af9d3e9a6f0", "rule": "else: return 'True'", "feature_idx": -1, "feature_name": "", "instances": 4, "metric": 0, "return_statement": 0, "tree_id": 1}, 
{"current_level": 8, "leaf_id": "87275a4c-4cc5-11ec-a9c9-3af9d3e9a6f0", "parents": "8717fa84-4cc5-11ec-a9c9-3af9d3e9a6f0", "rule": "if obj[0]>0:", "feature_idx": 0, "feature_name": "Passanger", "instances": 4, "metric": 0.8112781244591328, "return_statement": 0, "tree_id": 1}, 
{"current_level": 9, "leaf_id": "87275d26-4cc5-11ec-a9c9-3af9d3e9a6f0", "parents": "87275a4c-4cc5-11ec-a9c9-3af9d3e9a6f0", "rule": "return 'False'", "feature_idx": 0, "feature_name": "Passanger", "instances": 4, "metric": 0, "return_statement": 1, "tree_id": 1}, 
{"current_level": 8, "leaf_id": "872a4b6c-4cc5-11ec-a9c9-3af9d3e9a6f0", "parents": "8717fa84-4cc5-11ec-a9c9-3af9d3e9a6f0", "rule": "if obj[0]<=0:", "feature_idx": 0, "feature_name": "Passanger", "instances": 4, "metric": 0.8112781244591328, "return_statement": 0, "tree_id": 1}, 
{"current_level": 9, "leaf_id": "872a4d38-4cc5-11ec-a9c9-3af9d3e9a6f0", "parents": "872a4b6c-4cc5-11ec-a9c9-3af9d3e9a6f0", "rule": "return 'True'", "feature_idx": 0, "feature_name": "Passanger", "instances": 4, "metric": 0, "return_statement": 1, "tree_id": 1}, 
{"current_level": 5, "leaf_id": "8735a278-4cc5-11ec-a9c9-3af9d3e9a6f0", "parents": "85e498ac-4cc5-11ec-a9c9-3af9d3e9a6f0", "rule": "if obj[7]<=2:", "feature_idx": 7, "feature_name": "Occupation", "instances": 64, "metric": 0.7578784625383955, "return_statement": 0, "tree_id": 1}, 
{"current_level": 6, "leaf_id": "8735a836-4cc5-11ec-a9c9-3af9d3e9a6f0", "parents": "8735a278-4cc5-11ec-a9c9-3af9d3e9a6f0", "rule": "return 'True'", "feature_idx": 7, "feature_name": "Occupation", "instances": 64, "metric": 0, "return_statement": 1, "tree_id": 1}, 
{"current_level": 4, "leaf_id": "873b4cbe-4cc5-11ec-a9c9-3af9d3e9a6f0", "parents": "85c59128-4cc5-11ec-a9c9-3af9d3e9a6f0", "rule": "if obj[4]<=0:", "feature_idx": 4, "feature_name": "Age", "instances": 75, "metric": 0.8554508105601307, "return_statement": 0, "tree_id": 1}, 
{"current_level": 5, "leaf_id": "875280b4-4cc5-11ec-a9c9-3af9d3e9a6f0", "parents": "873b4cbe-4cc5-11ec-a9c9-3af9d3e9a6f0", "rule": "else: return 'False'", "feature_idx": -1, "feature_name": "", "instances": 11, "metric": 0, "return_statement": 0, "tree_id": 1}, 
{"current_level": 5, "leaf_id": "875b2d04-4cc5-11ec-a9c9-3af9d3e9a6f0", "parents": "873b4cbe-4cc5-11ec-a9c9-3af9d3e9a6f0", "rule": "if obj[1]>1:", "feature_idx": 1, "feature_name": "Time", "instances": 11, "metric": 0.9456603046006402, "return_statement": 0, "tree_id": 1}, 
{"current_level": 6, "leaf_id": "87685cea-4cc5-11ec-a9c9-3af9d3e9a6f0", "parents": "875b2d04-4cc5-11ec-a9c9-3af9d3e9a6f0", "rule": "else: return 'True'", "feature_idx": -1, "feature_name": "", "instances": 7, "metric": 0, "return_statement": 0, "tree_id": 1}, 
{"current_level": 6, "leaf_id": "876b95f4-4cc5-11ec-a9c9-3af9d3e9a6f0", "parents": "875b2d04-4cc5-11ec-a9c9-3af9d3e9a6f0", "rule": "if obj[0]<=2:", "feature_idx": 0, "feature_name": "Passanger", "instances": 7, "metric": 0.9852281360342516, "return_statement": 0, "tree_id": 1}, 
{"current_level": 7, "leaf_id": "87759572-4cc5-11ec-a9c9-3af9d3e9a6f0", "parents": "876b95f4-4cc5-11ec-a9c9-3af9d3e9a6f0", "rule": "else: return 'True'", "feature_idx": -1, "feature_name": "", "instances": 4, "metric": 0, "return_statement": 0, "tree_id": 1}, 
{"current_level": 7, "leaf_id": "8777982c-4cc5-11ec-a9c9-3af9d3e9a6f0", "parents": "876b95f4-4cc5-11ec-a9c9-3af9d3e9a6f0", "rule": "if obj[8]<=3:", "feature_idx": 8, "feature_name": "Income", "instances": 4, "metric": 0.8112781244591328, "return_statement": 0, "tree_id": 1}, 
{"current_level": 8, "leaf_id": "87779a34-4cc5-11ec-a9c9-3af9d3e9a6f0", "parents": "8777982c-4cc5-11ec-a9c9-3af9d3e9a6f0", "rule": "return 'False'", "feature_idx": 8, "feature_name": "Income", "instances": 4, "metric": 0, "return_statement": 1, "tree_id": 1}, 
{"current_level": 7, "leaf_id": "8779c070-4cc5-11ec-a9c9-3af9d3e9a6f0", "parents": "876b95f4-4cc5-11ec-a9c9-3af9d3e9a6f0", "rule": "if obj[8]>3:", "feature_idx": 8, "feature_name": "Income", "instances": 4, "metric": 0.8112781244591328, "return_statement": 0, "tree_id": 1}, 
{"current_level": 8, "leaf_id": "8779c23c-4cc5-11ec-a9c9-3af9d3e9a6f0", "parents": "8779c070-4cc5-11ec-a9c9-3af9d3e9a6f0", "rule": "return 'True'", "feature_idx": 8, "feature_name": "Income", "instances": 4, "metric": 0, "return_statement": 1, "tree_id": 1}, 
{"current_level": 6, "leaf_id": "877da7bc-4cc5-11ec-a9c9-3af9d3e9a6f0", "parents": "875b2d04-4cc5-11ec-a9c9-3af9d3e9a6f0", "rule": "if obj[0]>2:", "feature_idx": 0, "feature_name": "Passanger", "instances": 7, "metric": 0.9852281360342516, "return_statement": 0, "tree_id": 1}, 
{"current_level": 7, "leaf_id": "877da97e-4cc5-11ec-a9c9-3af9d3e9a6f0", "parents": "877da7bc-4cc5-11ec-a9c9-3af9d3e9a6f0", "rule": "return 'True'", "feature_idx": 0, "feature_name": "Passanger", "instances": 7, "metric": 0, "return_statement": 1, "tree_id": 1}, 
{"current_level": 5, "leaf_id": "87814476-4cc5-11ec-a9c9-3af9d3e9a6f0", "parents": "873b4cbe-4cc5-11ec-a9c9-3af9d3e9a6f0", "rule": "if obj[1]<=1:", "feature_idx": 1, "feature_name": "Time", "instances": 11, "metric": 0.9456603046006402, "return_statement": 0, "tree_id": 1}, 
{"current_level": 6, "leaf_id": "8781461a-4cc5-11ec-a9c9-3af9d3e9a6f0", "parents": "87814476-4cc5-11ec-a9c9-3af9d3e9a6f0", "rule": "return 'False'", "feature_idx": 1, "feature_name": "Time", "instances": 11, "metric": 0, "return_statement": 1, "tree_id": 1}, 
{"current_level": 3, "leaf_id": "87890936-4cc5-11ec-a9c9-3af9d3e9a6f0", "parents": "85a453aa-4cc5-11ec-a9c9-3af9d3e9a6f0", "rule": "if obj[6]>2:", "feature_idx": 6, "feature_name": "Education", "instances": 89, "metric": 0.9106223680988619, "return_statement": 0, "tree_id": 1}, 
{"current_level": 4, "leaf_id": "87ab01ee-4cc5-11ec-a9c9-3af9d3e9a6f0", "parents": "87890936-4cc5-11ec-a9c9-3af9d3e9a6f0", "rule": "else: return 'True'", "feature_idx": -1, "feature_name": "", "instances": 14, "metric": 0, "return_statement": 0, "tree_id": 1}, 
{"current_level": 4, "leaf_id": "87ad0ea8-4cc5-11ec-a9c9-3af9d3e9a6f0", "parents": "87890936-4cc5-11ec-a9c9-3af9d3e9a6f0", "rule": "if obj[4]>0:", "feature_idx": 4, "feature_name": "Age", "instances": 14, "metric": 0.9852281360342516, "return_statement": 0, "tree_id": 1}, 
{"current_level": 5, "leaf_id": "87c319a0-4cc5-11ec-a9c9-3af9d3e9a6f0", "parents": "87ad0ea8-4cc5-11ec-a9c9-3af9d3e9a6f0", "rule": "else: return 'True'", "feature_idx": -1, "feature_name": "", "instances": 11, "metric": 0, "return_statement": 0, "tree_id": 1}, 
{"current_level": 5, "leaf_id": "87c656c4-4cc5-11ec-a9c9-3af9d3e9a6f0", "parents": "87ad0ea8-4cc5-11ec-a9c9-3af9d3e9a6f0", "rule": "if obj[1]>1:", "feature_idx": 1, "feature_name": "Time", "instances": 11, "metric": 0.8453509366224365, "return_statement": 0, "tree_id": 1}, 
{"current_level": 6, "leaf_id": "87c658ae-4cc5-11ec-a9c9-3af9d3e9a6f0", "parents": "87c656c4-4cc5-11ec-a9c9-3af9d3e9a6f0", "rule": "return 'False'", "feature_idx": 1, "feature_name": "Time", "instances": 11, "metric": 0, "return_statement": 1, "tree_id": 1}, 
{"current_level": 5, "leaf_id": "87c8adfc-4cc5-11ec-a9c9-3af9d3e9a6f0", "parents": "87ad0ea8-4cc5-11ec-a9c9-3af9d3e9a6f0", "rule": "if obj[1]<=1:", "feature_idx": 1, "feature_name": "Time", "instances": 11, "metric": 0.8453509366224365, "return_statement": 0, "tree_id": 1}, 
{"current_level": 6, "leaf_id": "87da4fb2-4cc5-11ec-a9c9-3af9d3e9a6f0", "parents": "87c8adfc-4cc5-11ec-a9c9-3af9d3e9a6f0", "rule": "else: return 'False'", "feature_idx": -1, "feature_name": "", "instances": 5, "metric": 0, "return_statement": 0, "tree_id": 1}, 
{"current_level": 6, "leaf_id": "87de64b2-4cc5-11ec-a9c9-3af9d3e9a6f0", "parents": "87c8adfc-4cc5-11ec-a9c9-3af9d3e9a6f0", "rule": "if obj[10]>1.0:", "feature_idx": 10, "feature_name": "Coffeehouse", "instances": 5, "metric": 0.9709505944546686, "return_statement": 0, "tree_id": 1}, 
{"current_level": 7, "leaf_id": "87de66ce-4cc5-11ec-a9c9-3af9d3e9a6f0", "parents": "87de64b2-4cc5-11ec-a9c9-3af9d3e9a6f0", "rule": "return 'True'", "feature_idx": 10, "feature_name": "Coffeehouse", "instances": 5, "metric": 0, "return_statement": 1, "tree_id": 1}, 
{"current_level": 6, "leaf_id": "87e19a1a-4cc5-11ec-a9c9-3af9d3e9a6f0", "parents": "87c8adfc-4cc5-11ec-a9c9-3af9d3e9a6f0", "rule": "if obj[10]<=1.0:", "feature_idx": 10, "feature_name": "Coffeehouse", "instances": 5, "metric": 0.9709505944546686, "return_statement": 0, "tree_id": 1}, 
{"current_level": 7, "leaf_id": "87e19c68-4cc5-11ec-a9c9-3af9d3e9a6f0", "parents": "87e19a1a-4cc5-11ec-a9c9-3af9d3e9a6f0", "rule": "return 'False'", "feature_idx": 10, "feature_name": "Coffeehouse", "instances": 5, "metric": 0, "return_statement": 1, "tree_id": 1}, 
{"current_level": 4, "leaf_id": "87ea9c32-4cc5-11ec-a9c9-3af9d3e9a6f0", "parents": "87890936-4cc5-11ec-a9c9-3af9d3e9a6f0", "rule": "if obj[4]<=0:", "feature_idx": 4, "feature_name": "Age", "instances": 14, "metric": 0.9852281360342516, "return_statement": 0, "tree_id": 1}, 
{"current_level": 5, "leaf_id": "87ea9e44-4cc5-11ec-a9c9-3af9d3e9a6f0", "parents": "87ea9c32-4cc5-11ec-a9c9-3af9d3e9a6f0", "rule": "return 'True'", "feature_idx": 4, "feature_name": "Age", "instances": 14, "metric": 0, "return_statement": 1, "tree_id": 1}, 
{"current_level": 2, "leaf_id": "87f277f4-4cc5-11ec-a9c9-3af9d3e9a6f0", "parents": "857f3002-4cc5-11ec-a9c9-3af9d3e9a6f0", "rule": "if obj[9]<=-1.0:", "feature_idx": 9, "feature_name": "Bar", "instances": 91, "metric": 0.9254482516437046, "return_statement": 0, "tree_id": 1}, 
{"current_level": 3, "leaf_id": "87f279de-4cc5-11ec-a9c9-3af9d3e9a6f0", "parents": "87f277f4-4cc5-11ec-a9c9-3af9d3e9a6f0", "rule": "return 'False'", "feature_idx": 9, "feature_name": "Bar", "instances": 91, "metric": 0, "return_statement": 1, "tree_id": 1}, 
{"current_level": 1, "leaf_id": "87f745b8-4cc5-11ec-a9c9-3af9d3e9a6f0", "parents": "root", "rule": "if obj[2]<=1:", "feature_idx": 2, "feature_name": "Coupon", "instances": 127, "metric": 0.9801860005643561, "return_statement": 0, "tree_id": 1}, 
{"current_level": 2, "leaf_id": "882876e2-4cc5-11ec-a9c9-3af9d3e9a6f0", "parents": "87f745b8-4cc5-11ec-a9c9-3af9d3e9a6f0", "rule": "else: return 'True'", "feature_idx": -1, "feature_name": "", "instances": 36, "metric": 0, "return_statement": 0, "tree_id": 1}, 
{"current_level": 2, "leaf_id": "882c420e-4cc5-11ec-a9c9-3af9d3e9a6f0", "parents": "87f745b8-4cc5-11ec-a9c9-3af9d3e9a6f0", "rule": "if obj[7]>1:", "feature_idx": 7, "feature_name": "Occupation", "instances": 36, "metric": 0.9640787648082292, "return_statement": 0, "tree_id": 1}, 
{"current_level": 3, "leaf_id": "884bcc50-4cc5-11ec-a9c9-3af9d3e9a6f0", "parents": "882c420e-4cc5-11ec-a9c9-3af9d3e9a6f0", "rule": "else: return 'True'", "feature_idx": -1, "feature_name": "", "instances": 33, "metric": 0, "return_statement": 0, "tree_id": 1}, 
{"current_level": 3, "leaf_id": "884dcc30-4cc5-11ec-a9c9-3af9d3e9a6f0", "parents": "882c420e-4cc5-11ec-a9c9-3af9d3e9a6f0", "rule": "if obj[0]<=1:", "feature_idx": 0, "feature_name": "Passanger", "instances": 33, "metric": 0.9182958340544896, "return_statement": 0, "tree_id": 1}, 
{"current_level": 4, "leaf_id": "8868d642-4cc5-11ec-a9c9-3af9d3e9a6f0", "parents": "884dcc30-4cc5-11ec-a9c9-3af9d3e9a6f0", "rule": "else: return 'False'", "feature_idx": -1, "feature_name": "", "instances": 26, "metric": 0, "return_statement": 0, "tree_id": 1}, 
{"current_level": 4, "leaf_id": "886b77c6-4cc5-11ec-a9c9-3af9d3e9a6f0", "parents": "884dcc30-4cc5-11ec-a9c9-3af9d3e9a6f0", "rule": "if obj[6]<=2:", "feature_idx": 6, "feature_name": "Education", "instances": 26, "metric": 0.7793498372920852, "return_statement": 0, "tree_id": 1}, 
{"current_level": 5, "leaf_id": "888f4e4e-4cc5-11ec-a9c9-3af9d3e9a6f0", "parents": "886b77c6-4cc5-11ec-a9c9-3af9d3e9a6f0", "rule": "else: return 'False'", "feature_idx": -1, "feature_name": "", "instances": 21, "metric": 0, "return_statement": 0, "tree_id": 1}, 
{"current_level": 5, "leaf_id": "8892faf8-4cc5-11ec-a9c9-3af9d3e9a6f0", "parents": "886b77c6-4cc5-11ec-a9c9-3af9d3e9a6f0", "rule": "if obj[8]>2:", "feature_idx": 8, "feature_name": "Income", "instances": 21, "metric": 0.863120568566631, "return_statement": 0, "tree_id": 1}, 
{"current_level": 6, "leaf_id": "88ae10ea-4cc5-11ec-a9c9-3af9d3e9a6f0", "parents": "8892faf8-4cc5-11ec-a9c9-3af9d3e9a6f0", "rule": "else: return 'False'", "feature_idx": -1, "feature_name": "", "instances": 17, "metric": 0, "return_statement": 0, "tree_id": 1}, 
{"current_level": 6, "leaf_id": "88b0dd52-4cc5-11ec-a9c9-3af9d3e9a6f0", "parents": "8892faf8-4cc5-11ec-a9c9-3af9d3e9a6f0", "rule": "if obj[1]<=1:", "feature_idx": 1, "feature_name": "Time", "instances": 17, "metric": 0.9366673818775626, "return_statement": 0, "tree_id": 1}, 
{"current_level": 7, "leaf_id": "88c0666e-4cc5-11ec-a9c9-3af9d3e9a6f0", "parents": "88b0dd52-4cc5-11ec-a9c9-3af9d3e9a6f0", "rule": "else: return 'False'", "feature_idx": -1, "feature_name": "", "instances": 10, "metric": 0, "return_statement": 0, "tree_id": 1}, 
{"current_level": 7, "leaf_id": "88c2ab90-4cc5-11ec-a9c9-3af9d3e9a6f0", "parents": "88b0dd52-4cc5-11ec-a9c9-3af9d3e9a6f0", "rule": "if obj[4]<=2:", "feature_idx": 4, "feature_name": "Age", "instances": 10, "metric": 1.0, "return_statement": 0, "tree_id": 1}, 
{"current_level": 8, "leaf_id": "88caf44e-4cc5-11ec-a9c9-3af9d3e9a6f0", "parents": "88c2ab90-4cc5-11ec-a9c9-3af9d3e9a6f0", "rule": "else: return 'False'", "feature_idx": -1, "feature_name": "", "instances": 5, "metric": 0, "return_statement": 0, "tree_id": 1}, 
{"current_level": 8, "leaf_id": "88ccf816-4cc5-11ec-a9c9-3af9d3e9a6f0", "parents": "88c2ab90-4cc5-11ec-a9c9-3af9d3e9a6f0", "rule": "if obj[10]>1.0:", "feature_idx": 10, "feature_name": "Coffeehouse", "instances": 5, "metric": 0.7219280948873623, "return_statement": 0, "tree_id": 1}, 
{"current_level": 9, "leaf_id": "88ccfa14-4cc5-11ec-a9c9-3af9d3e9a6f0", "parents": "88ccf816-4cc5-11ec-a9c9-3af9d3e9a6f0", "rule": "return 'True'", "feature_idx": 10, "feature_name": "Coffeehouse", "instances": 5, "metric": 0, "return_statement": 1, "tree_id": 1}, 
{"current_level": 8, "leaf_id": "88cf5840-4cc5-11ec-a9c9-3af9d3e9a6f0", "parents": "88c2ab90-4cc5-11ec-a9c9-3af9d3e9a6f0", "rule": "if obj[10]<=1.0:", "feature_idx": 10, "feature_name": "Coffeehouse", "instances": 5, "metric": 0.7219280948873623, "return_statement": 0, "tree_id": 1}, 
{"current_level": 9, "leaf_id": "88cf5a0c-4cc5-11ec-a9c9-3af9d3e9a6f0", "parents": "88cf5840-4cc5-11ec-a9c9-3af9d3e9a6f0", "rule": "return 'False'", "feature_idx": 10, "feature_name": "Coffeehouse", "instances": 5, "metric": 0, "return_statement": 1, "tree_id": 1}, 
{"current_level": 7, "leaf_id": "88d3a508-4cc5-11ec-a9c9-3af9d3e9a6f0", "parents": "88b0dd52-4cc5-11ec-a9c9-3af9d3e9a6f0", "rule": "if obj[4]>2:", "feature_idx": 4, "feature_name": "Age", "instances": 10, "metric": 1.0, "return_statement": 0, "tree_id": 1}, 
{"current_level": 8, "leaf_id": "88dbca8a-4cc5-11ec-a9c9-3af9d3e9a6f0", "parents": "88d3a508-4cc5-11ec-a9c9-3af9d3e9a6f0", "rule": "else: return 'True'", "feature_idx": -1, "feature_name": "", "instances": 5, "metric": 0, "return_statement": 0, "tree_id": 1}, 
{"current_level": 8, "leaf_id": "88dee396-4cc5-11ec-a9c9-3af9d3e9a6f0", "parents": "88d3a508-4cc5-11ec-a9c9-3af9d3e9a6f0", "rule": "if obj[10]>0.0:", "feature_idx": 10, "feature_name": "Coffeehouse", "instances": 5, "metric": 0.7219280948873623, "return_statement": 0, "tree_id": 1}, 
{"current_level": 9, "leaf_id": "88dee56c-4cc5-11ec-a9c9-3af9d3e9a6f0", "parents": "88dee396-4cc5-11ec-a9c9-3af9d3e9a6f0", "rule": "return 'False'", "feature_idx": 10, "feature_name": "Coffeehouse", "instances": 5, "metric": 0, "return_statement": 1, "tree_id": 1}, 
{"current_level": 8, "leaf_id": "88e0e5a6-4cc5-11ec-a9c9-3af9d3e9a6f0", "parents": "88d3a508-4cc5-11ec-a9c9-3af9d3e9a6f0", "rule": "if obj[10]<=0.0:", "feature_idx": 10, "feature_name": "Coffeehouse", "instances": 5, "metric": 0.7219280948873623, "return_statement": 0, "tree_id": 1}, 
{"current_level": 9, "leaf_id": "88e0e772-4cc5-11ec-a9c9-3af9d3e9a6f0", "parents": "88e0e5a6-4cc5-11ec-a9c9-3af9d3e9a6f0", "rule": "return 'True'", "feature_idx": 10, "feature_name": "Coffeehouse", "instances": 5, "metric": 0, "return_statement": 1, "tree_id": 1}, 
{"current_level": 6, "leaf_id": "88e69ec4-4cc5-11ec-a9c9-3af9d3e9a6f0", "parents": "8892faf8-4cc5-11ec-a9c9-3af9d3e9a6f0", "rule": "if obj[1]>1:", "feature_idx": 1, "feature_name": "Time", "instances": 17, "metric": 0.9366673818775626, "return_statement": 0, "tree_id": 1}, 
{"current_level": 7, "leaf_id": "88f1568e-4cc5-11ec-a9c9-3af9d3e9a6f0", "parents": "88e69ec4-4cc5-11ec-a9c9-3af9d3e9a6f0", "rule": "else: return 'False'", "feature_idx": -1, "feature_name": "", "instances": 7, "metric": 0, "return_statement": 0, "tree_id": 1}, 
{"current_level": 7, "leaf_id": "88f48502-4cc5-11ec-a9c9-3af9d3e9a6f0", "parents": "88e69ec4-4cc5-11ec-a9c9-3af9d3e9a6f0", "rule": "if obj[3]<=0:", "feature_idx": 3, "feature_name": "Gender", "instances": 7, "metric": 0.5916727785823275, "return_statement": 0, "tree_id": 1}, 
{"current_level": 8, "leaf_id": "88f487f0-4cc5-11ec-a9c9-3af9d3e9a6f0", "parents": "88f48502-4cc5-11ec-a9c9-3af9d3e9a6f0", "rule": "return 'False'", "feature_idx": 3, "feature_name": "Gender", "instances": 7, "metric": 0, "return_statement": 1, "tree_id": 1}, 
{"current_level": 7, "leaf_id": "88f7386a-4cc5-11ec-a9c9-3af9d3e9a6f0", "parents": "88e69ec4-4cc5-11ec-a9c9-3af9d3e9a6f0", "rule": "if obj[3]>0:", "feature_idx": 3, "feature_name": "Gender", "instances": 7, "metric": 0.5916727785823275, "return_statement": 0, "tree_id": 1}, 
{"current_level": 8, "leaf_id": "88fe43e4-4cc5-11ec-a9c9-3af9d3e9a6f0", "parents": "88f7386a-4cc5-11ec-a9c9-3af9d3e9a6f0", "rule": "else: return 'True'", "feature_idx": -1, "feature_name": "", "instances": 3, "metric": 0, "return_statement": 0, "tree_id": 1}, 
{"current_level": 8, "leaf_id": "8901746a-4cc5-11ec-a9c9-3af9d3e9a6f0", "parents": "88f7386a-4cc5-11ec-a9c9-3af9d3e9a6f0", "rule": "if obj[4]<=0:", "feature_idx": 4, "feature_name": "Age", "instances": 3, "metric": 0.9182958340544896, "return_statement": 0, "tree_id": 1}, 
{"current_level": 9, "leaf_id": "89017744-4cc5-11ec-a9c9-3af9d3e9a6f0", "parents": "8901746a-4cc5-11ec-a9c9-3af9d3e9a6f0", "rule": "return 'False'", "feature_idx": 4, "feature_name": "Age", "instances": 3, "metric": 0, "return_statement": 1, "tree_id": 1}, 
{"current_level": 8, "leaf_id": "8904e212-4cc5-11ec-a9c9-3af9d3e9a6f0", "parents": "88f7386a-4cc5-11ec-a9c9-3af9d3e9a6f0", "rule": "if obj[4]>0:", "feature_idx": 4, "feature_name": "Age", "instances": 3, "metric": 0.9182958340544896, "return_statement": 0, "tree_id": 1}, 
{"current_level": 9, "leaf_id": "8904e50a-4cc5-11ec-a9c9-3af9d3e9a6f0", "parents": "8904e212-4cc5-11ec-a9c9-3af9d3e9a6f0", "rule": "return 'True'", "feature_idx": 4, "feature_name": "Age", "instances": 3, "metric": 0, "return_statement": 1, "tree_id": 1}, 
{"current_level": 5, "leaf_id": "8910df86-4cc5-11ec-a9c9-3af9d3e9a6f0", "parents": "886b77c6-4cc5-11ec-a9c9-3af9d3e9a6f0", "rule": "if obj[8]<=2:", "feature_idx": 8, "feature_name": "Income", "instances": 21, "metric": 0.863120568566631, "return_statement": 0, "tree_id": 1}, 
{"current_level": 6, "leaf_id": "8910e1a2-4cc5-11ec-a9c9-3af9d3e9a6f0", "parents": "8910df86-4cc5-11ec-a9c9-3af9d3e9a6f0", "rule": "return 'False'", "feature_idx": 8, "feature_name": "Income", "instances": 21, "metric": 0, "return_statement": 1, "tree_id": 1}, 
{"current_level": 4, "leaf_id": "891715b8-4cc5-11ec-a9c9-3af9d3e9a6f0", "parents": "884dcc30-4cc5-11ec-a9c9-3af9d3e9a6f0", "rule": "if obj[6]>2:", "feature_idx": 6, "feature_name": "Education", "instances": 26, "metric": 0.7793498372920852, "return_statement": 0, "tree_id": 1}, 
{"current_level": 5, "leaf_id": "891718b0-4cc5-11ec-a9c9-3af9d3e9a6f0", "parents": "891715b8-4cc5-11ec-a9c9-3af9d3e9a6f0", "rule": "return 'False'", "feature_idx": 6, "feature_name": "Education", "instances": 26, "metric": 0, "return_statement": 1, "tree_id": 1}, 
{"current_level": 3, "leaf_id": "891cd868-4cc5-11ec-a9c9-3af9d3e9a6f0", "parents": "882c420e-4cc5-11ec-a9c9-3af9d3e9a6f0", "rule": "if obj[0]>1:", "feature_idx": 0, "feature_name": "Passanger", "instances": 33, "metric": 0.9182958340544896, "return_statement": 0, "tree_id": 1}, 
{"current_level": 4, "leaf_id": "893081ec-4cc5-11ec-a9c9-3af9d3e9a6f0", "parents": "891cd868-4cc5-11ec-a9c9-3af9d3e9a6f0", "rule": "else: return 'False'", "feature_idx": -1, "feature_name": "", "instances": 7, "metric": 0, "return_statement": 0, "tree_id": 1}, 
{"current_level": 4, "leaf_id": "8933a368-4cc5-11ec-a9c9-3af9d3e9a6f0", "parents": "891cd868-4cc5-11ec-a9c9-3af9d3e9a6f0", "rule": "if obj[1]>2:", "feature_idx": 1, "feature_name": "Time", "instances": 7, "metric": 0.863120568566631, "return_statement": 0, "tree_id": 1}, 
{"current_level": 5, "leaf_id": "8933a5a2-4cc5-11ec-a9c9-3af9d3e9a6f0", "parents": "8933a368-4cc5-11ec-a9c9-3af9d3e9a6f0", "rule": "return 'True'", "feature_idx": 1, "feature_name": "Time", "instances": 7, "metric": 0, "return_statement": 1, "tree_id": 1}, 
{"current_level": 4, "leaf_id": "89362890-4cc5-11ec-a9c9-3af9d3e9a6f0", "parents": "891cd868-4cc5-11ec-a9c9-3af9d3e9a6f0", "rule": "if obj[1]<=2:", "feature_idx": 1, "feature_name": "Time", "instances": 7, "metric": 0.863120568566631, "return_statement": 0, "tree_id": 1}, 
{"current_level": 5, "leaf_id": "8940a9a0-4cc5-11ec-a9c9-3af9d3e9a6f0", "parents": "89362890-4cc5-11ec-a9c9-3af9d3e9a6f0", "rule": "else: return 'True'", "feature_idx": -1, "feature_name": "", "instances": 3, "metric": 0, "return_statement": 0, "tree_id": 1}, 
{"current_level": 5, "leaf_id": "89443b06-4cc5-11ec-a9c9-3af9d3e9a6f0", "parents": "89362890-4cc5-11ec-a9c9-3af9d3e9a6f0", "rule": "if obj[6]>0:", "feature_idx": 6, "feature_name": "Education", "instances": 3, "metric": 0.9182958340544896, "return_statement": 0, "tree_id": 1}, 
{"current_level": 6, "leaf_id": "89443cfa-4cc5-11ec-a9c9-3af9d3e9a6f0", "parents": "89443b06-4cc5-11ec-a9c9-3af9d3e9a6f0", "rule": "return 'False'", "feature_idx": 6, "feature_name": "Education", "instances": 3, "metric": 0, "return_statement": 1, "tree_id": 1}, 
{"current_level": 5, "leaf_id": "8946d726-4cc5-11ec-a9c9-3af9d3e9a6f0", "parents": "89362890-4cc5-11ec-a9c9-3af9d3e9a6f0", "rule": "if obj[6]<=0:", "feature_idx": 6, "feature_name": "Education", "instances": 3, "metric": 0.9182958340544896, "return_statement": 0, "tree_id": 1}, 
{"current_level": 6, "leaf_id": "8946d906-4cc5-11ec-a9c9-3af9d3e9a6f0", "parents": "8946d726-4cc5-11ec-a9c9-3af9d3e9a6f0", "rule": "return 'True'", "feature_idx": 6, "feature_name": "Education", "instances": 3, "metric": 0, "return_statement": 1, "tree_id": 1}, 
{"current_level": 2, "leaf_id": "89511ae2-4cc5-11ec-a9c9-3af9d3e9a6f0", "parents": "87f745b8-4cc5-11ec-a9c9-3af9d3e9a6f0", "rule": "if obj[7]<=1:", "feature_idx": 7, "feature_name": "Occupation", "instances": 36, "metric": 0.9640787648082292, "return_statement": 0, "tree_id": 1}, 
{"current_level": 3, "leaf_id": "89511d4e-4cc5-11ec-a9c9-3af9d3e9a6f0", "parents": "89511ae2-4cc5-11ec-a9c9-3af9d3e9a6f0", "rule": "return 'True'", "feature_idx": 7, "feature_name": "Occupation", "instances": 36, "metric": 0, "return_statement": 1, "tree_id": 1}
]