[
{"current_level": 1, "leaf_id": "56746232-4cc5-11ec-8fb4-3af9d3e9a6f0", "parents": "root", "rule": "else: return 'False'", "feature_idx": -1, "feature_name": "", "instances": 85, "metric": 0, "return_statement": 0, "tree_id": 10}, 
{"current_level": 1, "leaf_id": "5676cf5e-4cc5-11ec-8fb4-3af9d3e9a6f0", "parents": "root", "rule": "if obj[9]>0.0:", "feature_idx": 9, "feature_name": "Restaurant20to50", "instances": 85, "metric": 0.9951022712641691, "return_statement": 0, "tree_id": 10}, 
{"current_level": 2, "leaf_id": "5696212e-4cc5-11ec-8fb4-3af9d3e9a6f0", "parents": "5676cf5e-4cc5-11ec-8fb4-3af9d3e9a6f0", "rule": "else: return 'False'", "feature_idx": -1, "feature_name": "", "instances": 71, "metric": 0, "return_statement": 0, "tree_id": 10}, 
{"current_level": 2, "leaf_id": "5698020a-4cc5-11ec-8fb4-3af9d3e9a6f0", "parents": "5676cf5e-4cc5-11ec-8fb4-3af9d3e9a6f0", "rule": "if obj[7]>0.0:", "feature_idx": 7, "feature_name": "Bar", "instances": 71, "metric": 0.9756797868933085, "return_statement": 0, "tree_id": 10}, 
{"current_level": 3, "leaf_id": "56b11560-4cc5-11ec-8fb4-3af9d3e9a6f0", "parents": "5698020a-4cc5-11ec-8fb4-3af9d3e9a6f0", "rule": "else: return 'True'", "feature_idx": -1, "feature_name": "", "instances": 39, "metric": 0, "return_statement": 0, "tree_id": 10}, 
{"current_level": 3, "leaf_id": "56b4fafe-4cc5-11ec-8fb4-3af9d3e9a6f0", "parents": "5698020a-4cc5-11ec-8fb4-3af9d3e9a6f0", "rule": "if obj[4]<=2:", "feature_idx": 4, "feature_name": "Age", "instances": 39, "metric": 0.8582307926411411, "return_statement": 0, "tree_id": 10}, 
{"current_level": 4, "leaf_id": "56c8d380-4cc5-11ec-8fb4-3af9d3e9a6f0", "parents": "56b4fafe-4cc5-11ec-8fb4-3af9d3e9a6f0", "rule": "else: return 'False'", "feature_idx": -1, "feature_name": "", "instances": 20, "metric": 0, "return_statement": 0, "tree_id": 10}, 
{"current_level": 4, "leaf_id": "56cb1f46-4cc5-11ec-8fb4-3af9d3e9a6f0", "parents": "56b4fafe-4cc5-11ec-8fb4-3af9d3e9a6f0", "rule": "if obj[8]<=2.0:", "feature_idx": 8, "feature_name": "Coffeehouse", "instances": 20, "metric": 1.0, "return_statement": 0, "tree_id": 10}, 
{"current_level": 5, "leaf_id": "56da0f4c-4cc5-11ec-8fb4-3af9d3e9a6f0", "parents": "56cb1f46-4cc5-11ec-8fb4-3af9d3e9a6f0", "rule": "else: return 'False'", "feature_idx": -1, "feature_name": "", "instances": 12, "metric": 0, "return_statement": 0, "tree_id": 10}, 
{"current_level": 5, "leaf_id": "56dbd87c-4cc5-11ec-8fb4-3af9d3e9a6f0", "parents": "56cb1f46-4cc5-11ec-8fb4-3af9d3e9a6f0", "rule": "if obj[6]<=10:", "feature_idx": 6, "feature_name": "Occupation", "instances": 12, "metric": 0.9182958340544896, "return_statement": 0, "tree_id": 10}, 
{"current_level": 6, "leaf_id": "56e564aa-4cc5-11ec-8fb4-3af9d3e9a6f0", "parents": "56dbd87c-4cc5-11ec-8fb4-3af9d3e9a6f0", "rule": "else: return 'False'", "feature_idx": -1, "feature_name": "", "instances": 7, "metric": 0, "return_statement": 0, "tree_id": 10}, 
{"current_level": 6, "leaf_id": "56e73848-4cc5-11ec-8fb4-3af9d3e9a6f0", "parents": "56dbd87c-4cc5-11ec-8fb4-3af9d3e9a6f0", "rule": "if obj[0]<=1:", "feature_idx": 0, "feature_name": "Passanger", "instances": 7, "metric": 0.5916727785823275, "return_statement": 0, "tree_id": 10}, 
{"current_level": 7, "leaf_id": "56e739e2-4cc5-11ec-8fb4-3af9d3e9a6f0", "parents": "56e73848-4cc5-11ec-8fb4-3af9d3e9a6f0", "rule": "return 'True'", "feature_idx": 0, "feature_name": "Passanger", "instances": 7, "metric": 0, "return_statement": 1, "tree_id": 10}, 
{"current_level": 6, "leaf_id": "56e8d34c-4cc5-11ec-8fb4-3af9d3e9a6f0", "parents": "56dbd87c-4cc5-11ec-8fb4-3af9d3e9a6f0", "rule": "if obj[0]>1:", "feature_idx": 0, "feature_name": "Passanger", "instances": 7, "metric": 0.5916727785823275, "return_statement": 0, "tree_id": 10}, 
{"current_level": 7, "leaf_id": "56edd1da-4cc5-11ec-8fb4-3af9d3e9a6f0", "parents": "56e8d34c-4cc5-11ec-8fb4-3af9d3e9a6f0", "rule": "else: return 'True'", "feature_idx": -1, "feature_name": "", "instances": 2, "metric": 0, "return_statement": 0, "tree_id": 10}, 
{"current_level": 7, "leaf_id": "56efac80-4cc5-11ec-8fb4-3af9d3e9a6f0", "parents": "56e8d34c-4cc5-11ec-8fb4-3af9d3e9a6f0", "rule": "if obj[1]>0:", "feature_idx": 1, "feature_name": "Time", "instances": 2, "metric": 1.0, "return_statement": 0, "tree_id": 10}, 
{"current_level": 8, "leaf_id": "56efae1a-4cc5-11ec-8fb4-3af9d3e9a6f0", "parents": "56efac80-4cc5-11ec-8fb4-3af9d3e9a6f0", "rule": "return 'False'", "feature_idx": 1, "feature_name": "Time", "instances": 2, "metric": 0, "return_statement": 1, "tree_id": 10}, 
{"current_level": 7, "leaf_id": "56f15972-4cc5-11ec-8fb4-3af9d3e9a6f0", "parents": "56e8d34c-4cc5-11ec-8fb4-3af9d3e9a6f0", "rule": "if obj[1]<=0:", "feature_idx": 1, "feature_name": "Time", "instances": 2, "metric": 1.0, "return_statement": 0, "tree_id": 10}, 
{"current_level": 8, "leaf_id": "56f15b02-4cc5-11ec-8fb4-3af9d3e9a6f0", "parents": "56f15972-4cc5-11ec-8fb4-3af9d3e9a6f0", "rule": "return 'True'", "feature_idx": 1, "feature_name": "Time", "instances": 2, "metric": 0, "return_statement": 1, "tree_id": 10}, 
{"current_level": 5, "leaf_id": "56f559aa-4cc5-11ec-8fb4-3af9d3e9a6f0", "parents": "56cb1f46-4cc5-11ec-8fb4-3af9d3e9a6f0", "rule": "if obj[6]>10:", "feature_idx": 6, "feature_name": "Occupation", "instances": 12, "metric": 0.9182958340544896, "return_statement": 0, "tree_id": 10}, 
{"current_level": 6, "leaf_id": "56fee74a-4cc5-11ec-8fb4-3af9d3e9a6f0", "parents": "56f559aa-4cc5-11ec-8fb4-3af9d3e9a6f0", "rule": "else: return 'False'", "feature_idx": -1, "feature_name": "", "instances": 5, "metric": 0, "return_statement": 0, "tree_id": 10}, 
{"current_level": 6, "leaf_id": "57019094-4cc5-11ec-8fb4-3af9d3e9a6f0", "parents": "56f559aa-4cc5-11ec-8fb4-3af9d3e9a6f0", "rule": "if obj[1]<=0:", "feature_idx": 1, "feature_name": "Time", "instances": 5, "metric": 0.9709505944546686, "return_statement": 0, "tree_id": 10}, 
{"current_level": 7, "leaf_id": "5707caa4-4cc5-11ec-8fb4-3af9d3e9a6f0", "parents": "57019094-4cc5-11ec-8fb4-3af9d3e9a6f0", "rule": "else: return 'False'", "feature_idx": -1, "feature_name": "", "instances": 3, "metric": 0, "return_statement": 0, "tree_id": 10}, 
{"current_level": 7, "leaf_id": "570ab50c-4cc5-11ec-8fb4-3af9d3e9a6f0", "parents": "57019094-4cc5-11ec-8fb4-3af9d3e9a6f0", "rule": "if obj[2]<=2:", "feature_idx": 2, "feature_name": "Coupon", "instances": 3, "metric": 0.9182958340544896, "return_statement": 0, "tree_id": 10}, 
{"current_level": 8, "leaf_id": "570ab6d8-4cc5-11ec-8fb4-3af9d3e9a6f0", "parents": "570ab50c-4cc5-11ec-8fb4-3af9d3e9a6f0", "rule": "return 'True'", "feature_idx": 2, "feature_name": "Coupon", "instances": 3, "metric": 0, "return_statement": 1, "tree_id": 10}, 
{"current_level": 7, "leaf_id": "570c9b9c-4cc5-11ec-8fb4-3af9d3e9a6f0", "parents": "57019094-4cc5-11ec-8fb4-3af9d3e9a6f0", "rule": "if obj[2]>2:", "feature_idx": 2, "feature_name": "Coupon", "instances": 3, "metric": 0.9182958340544896, "return_statement": 0, "tree_id": 10}, 
{"current_level": 8, "leaf_id": "570c9d54-4cc5-11ec-8fb4-3af9d3e9a6f0", "parents": "570c9b9c-4cc5-11ec-8fb4-3af9d3e9a6f0", "rule": "return 'False'", "feature_idx": 2, "feature_name": "Coupon", "instances": 3, "metric": 0, "return_statement": 1, "tree_id": 10}, 
{"current_level": 6, "leaf_id": "57108612-4cc5-11ec-8fb4-3af9d3e9a6f0", "parents": "56f559aa-4cc5-11ec-8fb4-3af9d3e9a6f0", "rule": "if obj[1]>0:", "feature_idx": 1, "feature_name": "Time", "instances": 5, "metric": 0.9709505944546686, "return_statement": 0, "tree_id": 10}, 
{"current_level": 7, "leaf_id": "571087e8-4cc5-11ec-8fb4-3af9d3e9a6f0", "parents": "57108612-4cc5-11ec-8fb4-3af9d3e9a6f0", "rule": "return 'False'", "feature_idx": 1, "feature_name": "Time", "instances": 5, "metric": 0, "return_statement": 1, "tree_id": 10}, 
{"current_level": 4, "leaf_id": "5716ddbe-4cc5-11ec-8fb4-3af9d3e9a6f0", "parents": "56b4fafe-4cc5-11ec-8fb4-3af9d3e9a6f0", "rule": "if obj[8]>2.0:", "feature_idx": 8, "feature_name": "Coffeehouse", "instances": 20, "metric": 1.0, "return_statement": 0, "tree_id": 10}, 
{"current_level": 5, "leaf_id": "572383e8-4cc5-11ec-8fb4-3af9d3e9a6f0", "parents": "5716ddbe-4cc5-11ec-8fb4-3af9d3e9a6f0", "rule": "else: return 'False'", "feature_idx": -1, "feature_name": "", "instances": 8, "metric": 0, "return_statement": 0, "tree_id": 10}, 
{"current_level": 5, "leaf_id": "57276120-4cc5-11ec-8fb4-3af9d3e9a6f0", "parents": "5716ddbe-4cc5-11ec-8fb4-3af9d3e9a6f0", "rule": "if obj[1]>1:", "feature_idx": 1, "feature_name": "Time", "instances": 8, "metric": 0.8112781244591328, "return_statement": 0, "tree_id": 10}, 
{"current_level": 6, "leaf_id": "572f8774-4cc5-11ec-8fb4-3af9d3e9a6f0", "parents": "57276120-4cc5-11ec-8fb4-3af9d3e9a6f0", "rule": "else: return 'True'", "feature_idx": -1, "feature_name": "", "instances": 4, "metric": 0, "return_statement": 0, "tree_id": 10}, 
{"current_level": 6, "leaf_id": "5731a662-4cc5-11ec-8fb4-3af9d3e9a6f0", "parents": "57276120-4cc5-11ec-8fb4-3af9d3e9a6f0", "rule": "if obj[10]>0:", "feature_idx": 10, "feature_name": "Direction_same", "instances": 4, "metric": 1.0, "return_statement": 0, "tree_id": 10}, 
{"current_level": 7, "leaf_id": "5731a81a-4cc5-11ec-8fb4-3af9d3e9a6f0", "parents": "5731a662-4cc5-11ec-8fb4-3af9d3e9a6f0", "rule": "return 'False'", "feature_idx": 10, "feature_name": "Direction_same", "instances": 4, "metric": 0, "return_statement": 1, "tree_id": 10}, 
{"current_level": 6, "leaf_id": "5733b6a0-4cc5-11ec-8fb4-3af9d3e9a6f0", "parents": "57276120-4cc5-11ec-8fb4-3af9d3e9a6f0", "rule": "if obj[10]<=0:", "feature_idx": 10, "feature_name": "Direction_same", "instances": 4, "metric": 1.0, "return_statement": 0, "tree_id": 10}, 
{"current_level": 7, "leaf_id": "5733b862-4cc5-11ec-8fb4-3af9d3e9a6f0", "parents": "5733b6a0-4cc5-11ec-8fb4-3af9d3e9a6f0", "rule": "return 'True'", "feature_idx": 10, "feature_name": "Direction_same", "instances": 4, "metric": 0, "return_statement": 1, "tree_id": 10}, 
{"current_level": 5, "leaf_id": "573786cc-4cc5-11ec-8fb4-3af9d3e9a6f0", "parents": "5716ddbe-4cc5-11ec-8fb4-3af9d3e9a6f0", "rule": "if obj[1]<=1:", "feature_idx": 1, "feature_name": "Time", "instances": 8, "metric": 0.8112781244591328, "return_statement": 0, "tree_id": 10}, 
{"current_level": 6, "leaf_id": "5737888e-4cc5-11ec-8fb4-3af9d3e9a6f0", "parents": "573786cc-4cc5-11ec-8fb4-3af9d3e9a6f0", "rule": "return 'False'", "feature_idx": 1, "feature_name": "Time", "instances": 8, "metric": 0, "return_statement": 1, "tree_id": 10}, 
{"current_level": 3, "leaf_id": "573ccca4-4cc5-11ec-8fb4-3af9d3e9a6f0", "parents": "5698020a-4cc5-11ec-8fb4-3af9d3e9a6f0", "rule": "if obj[4]>2:", "feature_idx": 4, "feature_name": "Age", "instances": 39, "metric": 0.8582307926411411, "return_statement": 0, "tree_id": 10}, 
{"current_level": 4, "leaf_id": "574e0442-4cc5-11ec-8fb4-3af9d3e9a6f0", "parents": "573ccca4-4cc5-11ec-8fb4-3af9d3e9a6f0", "rule": "else: return 'True'", "feature_idx": -1, "feature_name": "", "instances": 19, "metric": 0, "return_statement": 0, "tree_id": 10}, 
{"current_level": 4, "leaf_id": "575094e6-4cc5-11ec-8fb4-3af9d3e9a6f0", "parents": "573ccca4-4cc5-11ec-8fb4-3af9d3e9a6f0", "rule": "if obj[1]<=2:", "feature_idx": 1, "feature_name": "Time", "instances": 19, "metric": 0.2974722489192897, "return_statement": 0, "tree_id": 10}, 
{"current_level": 5, "leaf_id": "5750968a-4cc5-11ec-8fb4-3af9d3e9a6f0", "parents": "575094e6-4cc5-11ec-8fb4-3af9d3e9a6f0", "rule": "return 'True'", "feature_idx": 1, "feature_name": "Time", "instances": 19, "metric": 0, "return_statement": 1, "tree_id": 10}, 
{"current_level": 4, "leaf_id": "575271b2-4cc5-11ec-8fb4-3af9d3e9a6f0", "parents": "573ccca4-4cc5-11ec-8fb4-3af9d3e9a6f0", "rule": "if obj[1]>2:", "feature_idx": 1, "feature_name": "Time", "instances": 19, "metric": 0.2974722489192897, "return_statement": 0, "tree_id": 10}, 
{"current_level": 5, "leaf_id": "575db194-4cc5-11ec-8fb4-3af9d3e9a6f0", "parents": "575271b2-4cc5-11ec-8fb4-3af9d3e9a6f0", "rule": "else: return 'False'", "feature_idx": -1, "feature_name": "", "instances": 5, "metric": 0, "return_statement": 0, "tree_id": 10}, 
{"current_level": 5, "leaf_id": "5760412a-4cc5-11ec-8fb4-3af9d3e9a6f0", "parents": "575271b2-4cc5-11ec-8fb4-3af9d3e9a6f0", "rule": "if obj[5]<=2:", "feature_idx": 5, "feature_name": "Education", "instances": 5, "metric": 0.7219280948873623, "return_statement": 0, "tree_id": 10}, 
{"current_level": 6, "leaf_id": "576042ec-4cc5-11ec-8fb4-3af9d3e9a6f0", "parents": "5760412a-4cc5-11ec-8fb4-3af9d3e9a6f0", "rule": "return 'True'", "feature_idx": 5, "feature_name": "Education", "instances": 5, "metric": 0, "return_statement": 1, "tree_id": 10}, 
{"current_level": 5, "leaf_id": "576222ce-4cc5-11ec-8fb4-3af9d3e9a6f0", "parents": "575271b2-4cc5-11ec-8fb4-3af9d3e9a6f0", "rule": "if obj[5]>2:", "feature_idx": 5, "feature_name": "Education", "instances": 5, "metric": 0.7219280948873623, "return_statement": 0, "tree_id": 10}, 
{"current_level": 6, "leaf_id": "57622490-4cc5-11ec-8fb4-3af9d3e9a6f0", "parents": "576222ce-4cc5-11ec-8fb4-3af9d3e9a6f0", "rule": "return 'False'", "feature_idx": 5, "feature_name": "Education", "instances": 5, "metric": 0, "return_statement": 1, "tree_id": 10}, 
{"current_level": 2, "leaf_id": "5768dd76-4cc5-11ec-8fb4-3af9d3e9a6f0", "parents": "5676cf5e-4cc5-11ec-8fb4-3af9d3e9a6f0", "rule": "if obj[7]<=0.0:", "feature_idx": 7, "feature_name": "Bar", "instances": 71, "metric": 0.9756797868933085, "return_statement": 0, "tree_id": 10}, 
{"current_level": 3, "leaf_id": "578100f4-4cc5-11ec-8fb4-3af9d3e9a6f0", "parents": "5768dd76-4cc5-11ec-8fb4-3af9d3e9a6f0", "rule": "else: return 'True'", "feature_idx": -1, "feature_name": "", "instances": 32, "metric": 0, "return_statement": 0, "tree_id": 10}, 
{"current_level": 3, "leaf_id": "5783f94e-4cc5-11ec-8fb4-3af9d3e9a6f0", "parents": "5768dd76-4cc5-11ec-8fb4-3af9d3e9a6f0", "rule": "if obj[0]<=2:", "feature_idx": 0, "feature_name": "Passanger", "instances": 32, "metric": 0.9886994082884974, "return_statement": 0, "tree_id": 10}, 
{"current_level": 4, "leaf_id": "579815a0-4cc5-11ec-8fb4-3af9d3e9a6f0", "parents": "5783f94e-4cc5-11ec-8fb4-3af9d3e9a6f0", "rule": "else: return 'True'", "feature_idx": -1, "feature_name": "", "instances": 24, "metric": 0, "return_statement": 0, "tree_id": 10}, 
{"current_level": 4, "leaf_id": "579bb3d6-4cc5-11ec-8fb4-3af9d3e9a6f0", "parents": "5783f94e-4cc5-11ec-8fb4-3af9d3e9a6f0", "rule": "if obj[11]>1:", "feature_idx": 11, "feature_name": "Distance", "instances": 24, "metric": 0.9182958340544896, "return_statement": 0, "tree_id": 10}, 
{"current_level": 5, "leaf_id": "57aad91a-4cc5-11ec-8fb4-3af9d3e9a6f0", "parents": "579bb3d6-4cc5-11ec-8fb4-3af9d3e9a6f0", "rule": "else: return 'False'", "feature_idx": -1, "feature_name": "", "instances": 13, "metric": 0, "return_statement": 0, "tree_id": 10}, 
{"current_level": 5, "leaf_id": "57adcada-4cc5-11ec-8fb4-3af9d3e9a6f0", "parents": "579bb3d6-4cc5-11ec-8fb4-3af9d3e9a6f0", "rule": "if obj[2]>2:", "feature_idx": 2, "feature_name": "Coupon", "instances": 13, "metric": 0.6193821946787638, "return_statement": 0, "tree_id": 10}, 
{"current_level": 6, "leaf_id": "57adcc88-4cc5-11ec-8fb4-3af9d3e9a6f0", "parents": "57adcada-4cc5-11ec-8fb4-3af9d3e9a6f0", "rule": "return 'False'", "feature_idx": 2, "feature_name": "Coupon", "instances": 13, "metric": 0, "return_statement": 1, "tree_id": 10}, 
{"current_level": 5, "leaf_id": "57af9eb4-4cc5-11ec-8fb4-3af9d3e9a6f0", "parents": "579bb3d6-4cc5-11ec-8fb4-3af9d3e9a6f0", "rule": "if obj[2]<=2:", "feature_idx": 2, "feature_name": "Coupon", "instances": 13, "metric": 0.6193821946787638, "return_statement": 0, "tree_id": 10}, 
{"current_level": 6, "leaf_id": "57b7777e-4cc5-11ec-8fb4-3af9d3e9a6f0", "parents": "57af9eb4-4cc5-11ec-8fb4-3af9d3e9a6f0", "rule": "else: return 'False'", "feature_idx": -1, "feature_name": "", "instances": 5, "metric": 0, "return_statement": 0, "tree_id": 10}, 
{"current_level": 6, "leaf_id": "57b95350-4cc5-11ec-8fb4-3af9d3e9a6f0", "parents": "57af9eb4-4cc5-11ec-8fb4-3af9d3e9a6f0", "rule": "if obj[5]>1:", "feature_idx": 5, "feature_name": "Education", "instances": 5, "metric": 0.9709505944546686, "return_statement": 0, "tree_id": 10}, 
{"current_level": 7, "leaf_id": "57be6070-4cc5-11ec-8fb4-3af9d3e9a6f0", "parents": "57b95350-4cc5-11ec-8fb4-3af9d3e9a6f0", "rule": "else: return 'False'", "feature_idx": -1, "feature_name": "", "instances": 3, "metric": 0, "return_statement": 0, "tree_id": 10}, 
{"current_level": 7, "leaf_id": "57c05cea-4cc5-11ec-8fb4-3af9d3e9a6f0", "parents": "57b95350-4cc5-11ec-8fb4-3af9d3e9a6f0", "rule": "if obj[1]<=1:", "feature_idx": 1, "feature_name": "Time", "instances": 3, "metric": 0.9182958340544896, "return_statement": 0, "tree_id": 10}, 
{"current_level": 8, "leaf_id": "57c05eb6-4cc5-11ec-8fb4-3af9d3e9a6f0", "parents": "57c05cea-4cc5-11ec-8fb4-3af9d3e9a6f0", "rule": "return 'True'", "feature_idx": 1, "feature_name": "Time", "instances": 3, "metric": 0, "return_statement": 1, "tree_id": 10}, 
{"current_level": 7, "leaf_id": "57c1fe38-4cc5-11ec-8fb4-3af9d3e9a6f0", "parents": "57b95350-4cc5-11ec-8fb4-3af9d3e9a6f0", "rule": "if obj[1]>1:", "feature_idx": 1, "feature_name": "Time", "instances": 3, "metric": 0.9182958340544896, "return_statement": 0, "tree_id": 10}, 
{"current_level": 8, "leaf_id": "57c1ffd2-4cc5-11ec-8fb4-3af9d3e9a6f0", "parents": "57c1fe38-4cc5-11ec-8fb4-3af9d3e9a6f0", "rule": "return 'False'", "feature_idx": 1, "feature_name": "Time", "instances": 3, "metric": 0, "return_statement": 1, "tree_id": 10}, 
{"current_level": 6, "leaf_id": "57c4b6b4-4cc5-11ec-8fb4-3af9d3e9a6f0", "parents": "57af9eb4-4cc5-11ec-8fb4-3af9d3e9a6f0", "rule": "if obj[5]<=1:", "feature_idx": 5, "feature_name": "Education", "instances": 5, "metric": 0.9709505944546686, "return_statement": 0, "tree_id": 10}, 
{"current_level": 7, "leaf_id": "57c4b858-4cc5-11ec-8fb4-3af9d3e9a6f0", "parents": "57c4b6b4-4cc5-11ec-8fb4-3af9d3e9a6f0", "rule": "return 'False'", "feature_idx": 5, "feature_name": "Education", "instances": 5, "metric": 0, "return_statement": 1, "tree_id": 10}, 
{"current_level": 4, "leaf_id": "57c8a0c6-4cc5-11ec-8fb4-3af9d3e9a6f0", "parents": "5783f94e-4cc5-11ec-8fb4-3af9d3e9a6f0", "rule": "if obj[11]<=1:", "feature_idx": 11, "feature_name": "Distance", "instances": 24, "metric": 0.9182958340544896, "return_statement": 0, "tree_id": 10}, 
{"current_level": 5, "leaf_id": "57d90dc6-4cc5-11ec-8fb4-3af9d3e9a6f0", "parents": "57c8a0c6-4cc5-11ec-8fb4-3af9d3e9a6f0", "rule": "else: return 'False'", "feature_idx": -1, "feature_name": "", "instances": 11, "metric": 0, "return_statement": 0, "tree_id": 10}, 
{"current_level": 5, "leaf_id": "57dcbf48-4cc5-11ec-8fb4-3af9d3e9a6f0", "parents": "57c8a0c6-4cc5-11ec-8fb4-3af9d3e9a6f0", "rule": "if obj[1]<=1:", "feature_idx": 1, "feature_name": "Time", "instances": 11, "metric": 0.9940302114769565, "return_statement": 0, "tree_id": 10}, 
{"current_level": 6, "leaf_id": "57e7c69a-4cc5-11ec-8fb4-3af9d3e9a6f0", "parents": "57dcbf48-4cc5-11ec-8fb4-3af9d3e9a6f0", "rule": "else: return 'False'", "feature_idx": -1, "feature_name": "", "instances": 6, "metric": 0, "return_statement": 0, "tree_id": 10}, 
{"current_level": 6, "leaf_id": "57eabea4-4cc5-11ec-8fb4-3af9d3e9a6f0", "parents": "57dcbf48-4cc5-11ec-8fb4-3af9d3e9a6f0", "rule": "if obj[6]<=8:", "feature_idx": 6, "feature_name": "Occupation", "instances": 6, "metric": 0.6500224216483541, "return_statement": 0, "tree_id": 10}, 
{"current_level": 7, "leaf_id": "57eac08e-4cc5-11ec-8fb4-3af9d3e9a6f0", "parents": "57eabea4-4cc5-11ec-8fb4-3af9d3e9a6f0", "rule": "return 'True'", "feature_idx": 6, "feature_name": "Occupation", "instances": 6, "metric": 0, "return_statement": 1, "tree_id": 10}, 
{"current_level": 6, "leaf_id": "57ece3aa-4cc5-11ec-8fb4-3af9d3e9a6f0", "parents": "57dcbf48-4cc5-11ec-8fb4-3af9d3e9a6f0", "rule": "if obj[6]>8:", "feature_idx": 6, "feature_name": "Occupation", "instances": 6, "metric": 0.6500224216483541, "return_statement": 0, "tree_id": 10}, 
{"current_level": 7, "leaf_id": "57ece58a-4cc5-11ec-8fb4-3af9d3e9a6f0", "parents": "57ece3aa-4cc5-11ec-8fb4-3af9d3e9a6f0", "rule": "return 'False'", "feature_idx": 6, "feature_name": "Occupation", "instances": 6, "metric": 0, "return_statement": 1, "tree_id": 10}, 
{"current_level": 5, "leaf_id": "57f0e842-4cc5-11ec-8fb4-3af9d3e9a6f0", "parents": "57c8a0c6-4cc5-11ec-8fb4-3af9d3e9a6f0", "rule": "if obj[1]>1:", "feature_idx": 1, "feature_name": "Time", "instances": 11, "metric": 0.9940302114769565, "return_statement": 0, "tree_id": 10}, 
{"current_level": 6, "leaf_id": "57fabc00-4cc5-11ec-8fb4-3af9d3e9a6f0", "parents": "57f0e842-4cc5-11ec-8fb4-3af9d3e9a6f0", "rule": "else: return 'True'", "feature_idx": -1, "feature_name": "", "instances": 5, "metric": 0, "return_statement": 0, "tree_id": 10}, 
{"current_level": 6, "leaf_id": "57fcbe9c-4cc5-11ec-8fb4-3af9d3e9a6f0", "parents": "57f0e842-4cc5-11ec-8fb4-3af9d3e9a6f0", "rule": "if obj[2]<=3:", "feature_idx": 2, "feature_name": "Coupon", "instances": 5, "metric": 0.7219280948873623, "return_statement": 0, "tree_id": 10}, 
{"current_level": 7, "leaf_id": "57fcc036-4cc5-11ec-8fb4-3af9d3e9a6f0", "parents": "57fcbe9c-4cc5-11ec-8fb4-3af9d3e9a6f0", "rule": "return 'False'", "feature_idx": 2, "feature_name": "Coupon", "instances": 5, "metric": 0, "return_statement": 1, "tree_id": 10}, 
{"current_level": 6, "leaf_id": "57fe5f68-4cc5-11ec-8fb4-3af9d3e9a6f0", "parents": "57f0e842-4cc5-11ec-8fb4-3af9d3e9a6f0", "rule": "if obj[2]>3:", "feature_idx": 2, "feature_name": "Coupon", "instances": 5, "metric": 0.7219280948873623, "return_statement": 0, "tree_id": 10}, 
{"current_level": 7, "leaf_id": "57fe6102-4cc5-11ec-8fb4-3af9d3e9a6f0", "parents": "57fe5f68-4cc5-11ec-8fb4-3af9d3e9a6f0", "rule": "return 'True'", "feature_idx": 2, "feature_name": "Coupon", "instances": 5, "metric": 0, "return_statement": 1, "tree_id": 10}, 
{"current_level": 3, "leaf_id": "580387b8-4cc5-11ec-8fb4-3af9d3e9a6f0", "parents": "5768dd76-4cc5-11ec-8fb4-3af9d3e9a6f0", "rule": "if obj[0]>2:", "feature_idx": 0, "feature_name": "Passanger", "instances": 32, "metric": 0.9886994082884974, "return_statement": 0, "tree_id": 10}, 
{"current_level": 4, "leaf_id": "58117bf2-4cc5-11ec-8fb4-3af9d3e9a6f0", "parents": "580387b8-4cc5-11ec-8fb4-3af9d3e9a6f0", "rule": "else: return 'False'", "feature_idx": -1, "feature_name": "", "instances": 8, "metric": 0, "return_statement": 0, "tree_id": 10}, 
{"current_level": 4, "leaf_id": "5813b958-4cc5-11ec-8fb4-3af9d3e9a6f0", "parents": "580387b8-4cc5-11ec-8fb4-3af9d3e9a6f0", "rule": "if obj[3]>0:", "feature_idx": 3, "feature_name": "Gender", "instances": 8, "metric": 0.8112781244591328, "return_statement": 0, "tree_id": 10}, 
{"current_level": 5, "leaf_id": "5813bb24-4cc5-11ec-8fb4-3af9d3e9a6f0", "parents": "5813b958-4cc5-11ec-8fb4-3af9d3e9a6f0", "rule": "return 'True'", "feature_idx": 3, "feature_name": "Gender", "instances": 8, "metric": 0, "return_statement": 1, "tree_id": 10}, 
{"current_level": 4, "leaf_id": "58156816-4cc5-11ec-8fb4-3af9d3e9a6f0", "parents": "580387b8-4cc5-11ec-8fb4-3af9d3e9a6f0", "rule": "if obj[3]<=0:", "feature_idx": 3, "feature_name": "Gender", "instances": 8, "metric": 0.8112781244591328, "return_statement": 0, "tree_id": 10}, 
{"current_level": 5, "leaf_id": "581d0c38-4cc5-11ec-8fb4-3af9d3e9a6f0", "parents": "58156816-4cc5-11ec-8fb4-3af9d3e9a6f0", "rule": "else: return 'True'", "feature_idx": -1, "feature_name": "", "instances": 3, "metric": 0, "return_statement": 0, "tree_id": 10}, 
{"current_level": 5, "leaf_id": "581ee2d8-4cc5-11ec-8fb4-3af9d3e9a6f0", "parents": "58156816-4cc5-11ec-8fb4-3af9d3e9a6f0", "rule": "if obj[4]<=2:", "feature_idx": 4, "feature_name": "Age", "instances": 3, "metric": 0.9182958340544896, "return_statement": 0, "tree_id": 10}, 
{"current_level": 6, "leaf_id": "581ee468-4cc5-11ec-8fb4-3af9d3e9a6f0", "parents": "581ee2d8-4cc5-11ec-8fb4-3af9d3e9a6f0", "rule": "return 'False'", "feature_idx": 4, "feature_name": "Age", "instances": 3, "metric": 0, "return_statement": 1, "tree_id": 10}, 
{"current_level": 5, "leaf_id": "582090b0-4cc5-11ec-8fb4-3af9d3e9a6f0", "parents": "58156816-4cc5-11ec-8fb4-3af9d3e9a6f0", "rule": "if obj[4]>2:", "feature_idx": 4, "feature_name": "Age", "instances": 3, "metric": 0.9182958340544896, "return_statement": 0, "tree_id": 10}, 
{"current_level": 6, "leaf_id": "58209240-4cc5-11ec-8fb4-3af9d3e9a6f0", "parents": "582090b0-4cc5-11ec-8fb4-3af9d3e9a6f0", "rule": "return 'True'", "feature_idx": 4, "feature_name": "Age", "instances": 3, "metric": 0, "return_statement": 1, "tree_id": 10}, 
{"current_level": 1, "leaf_id": "582776a0-4cc5-11ec-8fb4-3af9d3e9a6f0", "parents": "root", "rule": "if obj[9]<=0.0:", "feature_idx": 9, "feature_name": "Restaurant20to50", "instances": 85, "metric": 0.9951022712641691, "return_statement": 0, "tree_id": 10}, 
{"current_level": 2, "leaf_id": "583b64ee-4cc5-11ec-8fb4-3af9d3e9a6f0", "parents": "582776a0-4cc5-11ec-8fb4-3af9d3e9a6f0", "rule": "else: return 'False'", "feature_idx": -1, "feature_name": "", "instances": 14, "metric": 0, "return_statement": 0, "tree_id": 10}, 
{"current_level": 2, "leaf_id": "583d4048-4cc5-11ec-8fb4-3af9d3e9a6f0", "parents": "582776a0-4cc5-11ec-8fb4-3af9d3e9a6f0", "rule": "if obj[6]>6:", "feature_idx": 6, "feature_name": "Occupation", "instances": 14, "metric": 0.863120568566631, "return_statement": 0, "tree_id": 10}, 
{"current_level": 3, "leaf_id": "584b9b66-4cc5-11ec-8fb4-3af9d3e9a6f0", "parents": "583d4048-4cc5-11ec-8fb4-3af9d3e9a6f0", "rule": "else: return 'True'", "feature_idx": -1, "feature_name": "", "instances": 7, "metric": 0, "return_statement": 0, "tree_id": 10}, 
{"current_level": 3, "leaf_id": "584d6658-4cc5-11ec-8fb4-3af9d3e9a6f0", "parents": "583d4048-4cc5-11ec-8fb4-3af9d3e9a6f0", "rule": "if obj[4]>1:", "feature_idx": 4, "feature_name": "Age", "instances": 7, "metric": 0.9852281360342516, "return_statement": 0, "tree_id": 10}, 
{"current_level": 4, "leaf_id": "585784bc-4cc5-11ec-8fb4-3af9d3e9a6f0", "parents": "584d6658-4cc5-11ec-8fb4-3af9d3e9a6f0", "rule": "else: return 'True'", "feature_idx": -1, "feature_name": "", "instances": 4, "metric": 0, "return_statement": 0, "tree_id": 10}, 
{"current_level": 4, "leaf_id": "585955d0-4cc5-11ec-8fb4-3af9d3e9a6f0", "parents": "584d6658-4cc5-11ec-8fb4-3af9d3e9a6f0", "rule": "if obj[0]<=1:", "feature_idx": 0, "feature_name": "Passanger", "instances": 4, "metric": 0.8112781244591328, "return_statement": 0, "tree_id": 10}, 
{"current_level": 5, "leaf_id": "5859576a-4cc5-11ec-8fb4-3af9d3e9a6f0", "parents": "585955d0-4cc5-11ec-8fb4-3af9d3e9a6f0", "rule": "return 'False'", "feature_idx": 0, "feature_name": "Passanger", "instances": 4, "metric": 0, "return_statement": 1, "tree_id": 10}, 
{"current_level": 4, "leaf_id": "585ae7e2-4cc5-11ec-8fb4-3af9d3e9a6f0", "parents": "584d6658-4cc5-11ec-8fb4-3af9d3e9a6f0", "rule": "if obj[0]>1:", "feature_idx": 0, "feature_name": "Passanger", "instances": 4, "metric": 0.8112781244591328, "return_statement": 0, "tree_id": 10}, 
{"current_level": 5, "leaf_id": "585ae97c-4cc5-11ec-8fb4-3af9d3e9a6f0", "parents": "585ae7e2-4cc5-11ec-8fb4-3af9d3e9a6f0", "rule": "return 'True'", "feature_idx": 0, "feature_name": "Passanger", "instances": 4, "metric": 0, "return_statement": 1, "tree_id": 10}, 
{"current_level": 3, "leaf_id": "585d85f6-4cc5-11ec-8fb4-3af9d3e9a6f0", "parents": "583d4048-4cc5-11ec-8fb4-3af9d3e9a6f0", "rule": "if obj[4]<=1:", "feature_idx": 4, "feature_name": "Age", "instances": 7, "metric": 0.9852281360342516, "return_statement": 0, "tree_id": 10}, 
{"current_level": 4, "leaf_id": "585d877c-4cc5-11ec-8fb4-3af9d3e9a6f0", "parents": "585d85f6-4cc5-11ec-8fb4-3af9d3e9a6f0", "rule": "return 'True'", "feature_idx": 4, "feature_name": "Age", "instances": 7, "metric": 0, "return_statement": 1, "tree_id": 10}, 
{"current_level": 2, "leaf_id": "586013a2-4cc5-11ec-8fb4-3af9d3e9a6f0", "parents": "582776a0-4cc5-11ec-8fb4-3af9d3e9a6f0", "rule": "if obj[6]<=6:", "feature_idx": 6, "feature_name": "Occupation", "instances": 14, "metric": 0.863120568566631, "return_statement": 0, "tree_id": 10}, 
{"current_level": 3, "leaf_id": "58601528-4cc5-11ec-8fb4-3af9d3e9a6f0", "parents": "586013a2-4cc5-11ec-8fb4-3af9d3e9a6f0", "rule": "return 'False'", "feature_idx": 6, "feature_name": "Occupation", "instances": 14, "metric": 0, "return_statement": 1, "tree_id": 10}
]