[
{"current_level": 1, "leaf_id": "8f4a0a22-4cc4-11ec-a1df-3af9d3e9a6f0", "parents": "root", "rule": "else: return 'False'", "feature_idx": -1, "feature_name": "", "instances": 23, "metric": 0, "return_statement": 0, "tree_id": 6}, 
{"current_level": 1, "leaf_id": "8f5616e6-4cc4-11ec-a1df-3af9d3e9a6f0", "parents": "root", "rule": "if obj[0]<=3:", "feature_idx": 0, "feature_name": "Coupon", "instances": 23, "metric": 0.9876925088958034, "return_statement": 0, "tree_id": 6}, 
{"current_level": 2, "leaf_id": "8f5967b0-4cc4-11ec-a1df-3af9d3e9a6f0", "parents": "8f5616e6-4cc4-11ec-a1df-3af9d3e9a6f0", "rule": "else: return 'False'", "feature_idx": -1, "feature_name": "", "instances": 18, "metric": 0, "return_statement": 0, "tree_id": 6}, 
{"current_level": 2, "leaf_id": "8f5d4830-4cc4-11ec-a1df-3af9d3e9a6f0", "parents": "8f5616e6-4cc4-11ec-a1df-3af9d3e9a6f0", "rule": "if obj[1]<=2:", "feature_idx": 1, "feature_name": "Education", "instances": 18, "metric": 1.0, "return_statement": 0, "tree_id": 6}, 
{"current_level": 3, "leaf_id": "8f5d4b3c-4cc4-11ec-a1df-3af9d3e9a6f0", "parents": "8f5d4830-4cc4-11ec-a1df-3af9d3e9a6f0", "rule": "return 'True'", "feature_idx": 1, "feature_name": "Education", "instances": 18, "metric": 0, "return_statement": 1, "tree_id": 6}, 
{"current_level": 2, "leaf_id": "8f61efac-4cc4-11ec-a1df-3af9d3e9a6f0", "parents": "8f5616e6-4cc4-11ec-a1df-3af9d3e9a6f0", "rule": "if obj[1]>2:", "feature_idx": 1, "feature_name": "Education", "instances": 18, "metric": 1.0, "return_statement": 0, "tree_id": 6}, 
{"current_level": 3, "leaf_id": "8f61f2d6-4cc4-11ec-a1df-3af9d3e9a6f0", "parents": "8f61efac-4cc4-11ec-a1df-3af9d3e9a6f0", "rule": "return 'False'", "feature_idx": 1, "feature_name": "Education", "instances": 18, "metric": 0, "return_statement": 1, "tree_id": 6}, 
{"current_level": 1, "leaf_id": "8f693e74-4cc4-11ec-a1df-3af9d3e9a6f0", "parents": "root", "rule": "if obj[0]>3:", "feature_idx": 0, "feature_name": "Coupon", "instances": 23, "metric": 0.9876925088958034, "return_statement": 0, "tree_id": 6}, 
{"current_level": 2, "leaf_id": "8f6b84cc-4cc4-11ec-a1df-3af9d3e9a6f0", "parents": "8f693e74-4cc4-11ec-a1df-3af9d3e9a6f0", "rule": "else: return 'False'", "feature_idx": -1, "feature_name": "", "instances": 5, "metric": 0, "return_statement": 0, "tree_id": 6}, 
{"current_level": 2, "leaf_id": "8f711edc-4cc4-11ec-a1df-3af9d3e9a6f0", "parents": "8f693e74-4cc4-11ec-a1df-3af9d3e9a6f0", "rule": "if obj[1]<=2:", "feature_idx": 1, "feature_name": "Education", "instances": 5, "metric": 0.7219280948873623, "return_statement": 0, "tree_id": 6}, 
{"current_level": 3, "leaf_id": "8f71218e-4cc4-11ec-a1df-3af9d3e9a6f0", "parents": "8f711edc-4cc4-11ec-a1df-3af9d3e9a6f0", "rule": "return 'False'", "feature_idx": 1, "feature_name": "Education", "instances": 5, "metric": 0, "return_statement": 1, "tree_id": 6}, 
{"current_level": 2, "leaf_id": "8f73cc7c-4cc4-11ec-a1df-3af9d3e9a6f0", "parents": "8f693e74-4cc4-11ec-a1df-3af9d3e9a6f0", "rule": "if obj[1]>2:", "feature_idx": 1, "feature_name": "Education", "instances": 5, "metric": 0.7219280948873623, "return_statement": 0, "tree_id": 6}, 
{"current_level": 3, "leaf_id": "8f73ce84-4cc4-11ec-a1df-3af9d3e9a6f0", "parents": "8f73cc7c-4cc4-11ec-a1df-3af9d3e9a6f0", "rule": "return 'False'", "feature_idx": 1, "feature_name": "Education", "instances": 5, "metric": 0, "return_statement": 1, "tree_id": 6}
]